{"root": {"\ubc95\ub839": {"@\ubc95\ub839\ud0a4": "0002662018061215680", "\uae30\ubcf8\uc815\ubcf4": {"\ubc95\ub839ID": "000266", "\uacf5\ud3ec\uc77c\uc790": "20180612", "\uacf5\ud3ec\ubc88\ud638": "15680", "\uc5b8\uc5b4": "\ud55c\uae00", "\ubc95\uc885\uad6c\ubd84": {"@\ubc95\uc885\uad6c\ubd84\ucf54\ub4dc": "A0002", "#text": "\ubc95\ub960"}, "\ubc95\ub839\uba85_\ud55c\uae00": "\uc218\ub3c4\uad8c\uc815\ube44\uacc4\ud68d\ubc95", "\ubc95\ub839\uba85_\ud55c\uc790": "\uc218\ub3c4\uad8c\uc815\ube44\uacc4\ud68d\ubc95", "\ubc95\ub839\uba85\uc57d\uce6d": null, "\uc81c\uba85\ubcc0\uacbd\uc5ec\ubd80": "N", "\ud55c\uae00\ubc95\ub839\uc5ec\ubd80": "N", "\ud3b8\uc7a5\uc808\uad00": "33020100", "\uc18c\uad00\ubd80\ucc98": {"@\uc18c\uad00\ubd80\ucc98\ucf54\ub4dc": "1613000", "#text": "\uad6d\ud1a0\uad50\ud1b5\ubd80"}, "\uc2dc\ud589\uc77c\uc790": "20180612", "\uc81c\uac1c\uc815\uad6c\ubd84": "\uc77c\ubd80\uac1c\uc815", "\ubcc4\ud45c\ud3b8\uc9d1\uc5ec\ubd80": "N", "\uacf5\ud3ec\ubc95\ub839\uc5ec\ubd80": "Y"}, "\uc870\ubb38": {"\uc870\ubb38\ub2e8\uc704": [{"@\uc870\ubb38\ud0a4": "0001001", "\uc870\ubb38\ubc88\ud638": "1", "\uc870\ubb38\uc5ec\ubd80": "\uc870\ubb38", "\uc870\ubb38\uc81c\ubaa9": "\ubaa9\uc801", "\uc870\ubb38\uc2dc\ud589\uc77c\uc790": "20180612", "\uc870\ubb38\uc774\ub3d9\uc774\uc804": "000000", "\uc870\ubb38\uc774\ub3d9\uc774\ud6c4": "000000", "\uc870\ubb38\ubcc0\uacbd\uc5ec\ubd80": null, "\uc870\ubb38\ub0b4\uc6a9": "\uc81c1\uc870(\ubaa9\uc801) \uc774 \ubc95\uc740 \uc218\ub3c4\uad8c(\u9996\u90fd\u5708) \uc815\ube44\uc5d0 \uad00\ud55c \uc885\ud569\uc801\uc778 \uacc4\ud68d\uc758 \uc218\ub9bd\uacfc \uc2dc\ud589\uc5d0 \ud544\uc694\ud55c \uc0ac\ud56d\uc744 \uc815\ud568\uc73c\ub85c\uc368 \uc218\ub3c4\uad8c\uc5d0 \uacfc\ub3c4\ud558\uac8c \uc9d1\uc911\ub41c \uc778\uad6c\uc640 \uc0b0\uc5c5\uc744 \uc801\uc815\ud558\uac8c \ubc30\uce58\ud558\ub3c4\ub85d \uc720\ub3c4\ud558\uc5ec \uc218\ub3c4\uad8c\uc744 \uc9c8\uc11c \uc788\uac8c \uc815\ube44\ud558\uace0 \uade0\ud615 \uc788\uac8c \ubc1c\uc804\uc2dc\ud0a4\ub294 \uac83\uc744 \ubaa9\uc801\uc73c\ub85c \ud55c\ub2e4."}, {"@\uc870\ubb38\ud0a4": "0002001", "\uc870\ubb38\ubc88\ud638": "2", "\uc870\ubb38\uc5ec\ubd80": "\uc870\ubb38", "\uc870\ubb38\uc81c\ubaa9": "\uc815\uc758", "\uc870\ubb38\uc2dc\ud589\uc77c\uc790": "20180612", "\uc870\ubb38\uc774\ub3d9\uc774\uc804": "000000", "\uc870\ubb38\uc774\ub3d9\uc774\ud6c4": "000000", "\uc870\ubb38\ubcc0\uacbd\uc5ec\ubd80": null, "\uc870\ubb38\ub0b4\uc6a9": "\uc81c2\uc870(\uc815\uc758) \uc774 \ubc95\uc5d0\uc11c \uc0ac\uc6a9\ud558\ub294 \uc6a9\uc5b4\uc758 \ub73b\uc740 \ub2e4\uc74c\uacfc \uac19\ub2e4.", "\ud56d": {"\ud638": [{"\ud638\ubc88\ud638": "1.", "\ud638\ub0b4\uc6a9": "1. \"\uc218\ub3c4\uad8c\"\uc774\ub780 \uc11c\uc6b8\ud2b9\ubcc4\uc2dc\uc640 \ub300\ud1b5\ub839\ub839\uc73c\ub85c \uc815\ud558\ub294 \uadf8 \uc8fc\ubcc0 \uc9c0\uc5ed\uc744 \ub9d0\ud55c\ub2e4."}, {"\ud638\ubc88\ud638": "2.", "\ud638\ub0b4\uc6a9": "2. \"\uc218\ub3c4\uad8c\uc815\ube44\uacc4\ud68d\"\uc774\ub780 \u300c\uad6d\ud1a0\uae30\ubcf8\ubc95\u300d \uc81c6\uc870\uc81c2\ud56d\uc81c1\ud638\uc5d0 \ub530\ub978 \uad6d\ud1a0\uc885\ud569\uacc4\ud68d\uc744 \uae30\ubcf8\uc73c\ub85c \ud558\uc5ec \uc81c4\uc870\uc5d0 \ub530\ub77c \uc218\ub9bd\ub418\ub294 \uacc4\ud68d\uc744 \ub9d0\ud55c\ub2e4."}, {"\ud638\ubc88\ud638": "3.", "\ud638\ub0b4\uc6a9": "3. \"\uc778\uad6c\uc9d1\uc911\uc720\ubc1c\uc2dc\uc124\"\uc774\ub780 \ud559\uad50, \uacf5\uc7a5, \uacf5\uacf5 \uccad\uc0ac, \uc5c5\ubb34\uc6a9 \uac74\ucd95\ubb3c, \ud310\ub9e4\uc6a9 \uac74\ucd95\ubb3c, \uc5f0\uc218 \uc2dc\uc124, \uadf8 \ubc16\uc5d0 \uc778\uad6c \uc9d1\uc911\uc744 \uc720\ubc1c\ud558\ub294 \uc2dc\uc124\ub85c\uc11c \ub300\ud1b5\ub839\ub839\uc73c\ub85c \uc815\ud558\ub294 \uc885\ub958 \ubc0f \uaddc\ubaa8 \uc774\uc0c1\uc758 \uc2dc\uc124\uc744 \ub9d0\ud55c\ub2e4."}, {"\ud638\ubc88\ud638": "4.", "\ud638\ub0b4\uc6a9": "4. \"\ub300\uaddc\ubaa8\uac1c\ubc1c\uc0ac\uc5c5\"\uc774\ub780 \ud0dd\uc9c0, \uacf5\uc5c5 \uc6a9\uc9c0 \ubc0f \uad00\uad11\uc9c0 \ub4f1\uc744 \uc870\uc131\ud560 \ubaa9\uc801\uc73c\ub85c \ud558\ub294 \uc0ac\uc5c5\uc73c\ub85c\uc11c \ub300\ud1b5\ub839\ub839\uc73c\ub85c \uc815\ud558\ub294 \uc885\ub958 \ubc0f \uaddc\ubaa8 \uc774\uc0c1\uc758 \uc0ac\uc5c5\uc744 \ub9d0\ud55c\ub2e4."}, {"\ud638\ubc88\ud638": "5.", "\ud638\ub0b4\uc6a9": "5. \"\uacf5\uc5c5\uc9c0\uc5ed\"\uc774\ub780 \ub2e4\uc74c \uac01 \ubaa9\uc758 \uc9c0\uc5ed\uc744 \ub9d0\ud55c\ub2e4.", "\ubaa9": [{"\ubaa9\ubc88\ud638": "\uac00.", "\ubaa9\ub0b4\uc6a9": "\uac00. \u300c\uad6d\ud1a0\uc758 \uacc4\ud68d \ubc0f \uc774\uc6a9\uc5d0 \uad00\ud55c \ubc95\ub960\u300d\uc5d0 \ub530\ub77c \uc9c0\uc815\ub41c \uacf5\uc5c5\uc9c0\uc5ed"}, {"\ubaa9\ubc88\ud638": "\ub098.", "\ubaa9\ub0b4\uc6a9": "\ub098. \u300c\uad6d\ud1a0\uc758 \uacc4\ud68d \ubc0f \uc774\uc6a9\uc5d0 \uad00\ud55c \ubc95\ub960\u300d\uacfc \uadf8 \ubc16\uc758 \uad00\uacc4 \ubc95\ub960\uc5d0 \ub530\ub77c \uacf5\uc5c5 \uc6a9\uc9c0\uc640 \uc774\uc5d0 \ub538\ub9b0 \uc6a9\ub3c4\ub85c \uc774\uc6a9\ub418\uace0 \uc788\uac70\ub098 \uc774\uc6a9\ub420 \uc77c\ub2e8(\u4e00\u5718)\uc758 \uc9c0\uc5ed\uc73c\ub85c\uc11c \ub300\ud1b5\ub839\ub839\uc73c\ub85c \uc815\ud558\ub294 \uc885\ub958 \ubc0f \uaddc\ubaa8 \uc774\uc0c1\uc758 \uc9c0\uc5ed"}]}]}}, {"@\uc870\ubb38\ud0a4": "0003001", "\uc870\ubb38\ubc88\ud638": "3", "\uc870\ubb38\uc5ec\ubd80": "\uc870\ubb38", "\uc870\ubb38\uc81c\ubaa9": "\ub2e4\ub978 \uacc4\ud68d \ub4f1\uacfc\uc758 \uad00\uacc4", "\uc870\ubb38\uc2dc\ud589\uc77c\uc790": "20180612", "\uc870\ubb38\uc774\ub3d9\uc774\uc804": "000000", "\uc870\ubb38\uc774\ub3d9\uc774\ud6c4": "000000", "\uc870\ubb38\ubcc0\uacbd\uc5ec\ubd80": null, "\uc870\ubb38\ub0b4\uc6a9": "\uc81c3\uc870(\ub2e4\ub978 \uacc4\ud68d \ub4f1\uacfc\uc758 \uad00\uacc4)", "\ud56d": [{"\ud56d\ubc88\ud638": "\u2460", "\ud56d\ub0b4\uc6a9": "\u2460 \uc218\ub3c4\uad8c\uc815\ube44\uacc4\ud68d\uc740 \uc218\ub3c4\uad8c\uc758 \u300c\uad6d\ud1a0\uc758 \uacc4\ud68d \ubc0f \uc774\uc6a9\uc5d0 \uad00\ud55c \ubc95\ub960\u300d\uc5d0 \ub530\ub978 \ub3c4\uc2dc\u318d\uad70\uacc4\ud68d, \uadf8 \ubc16\uc758 \ub2e4\ub978 \ubc95\ub839\uc5d0 \ub530\ub978 \ud1a0\uc9c0 \uc774\uc6a9 \uacc4\ud68d \ub610\ub294 \uac1c\ubc1c \uacc4\ud68d \ub4f1\uc5d0 \uc6b0\uc120\ud558\uba70, \uadf8 \uacc4\ud68d\uc758 \uae30\ubcf8\uc774 \ub41c\ub2e4. \ub2e4\ub9cc, \uc218\ub3c4\uad8c\uc758 \uad70\uc0ac\uc5d0 \uad00\ud55c \uc0ac\ud56d\uc5d0 \ub300\ud558\uc5ec\ub294 \uadf8\ub7ec\ud558\uc9c0 \uc544\ub2c8\ud558\ub2e4. <\uac1c\uc815 2011.4.14>"}, {"\ud56d\ubc88\ud638": "\u2461", "\ud56d\ub0b4\uc6a9": "\u2461 \uc911\uc559\ud589\uc815\uae30\uad00\uc758 \uc7a5\uc774\ub098 \uc11c\uc6b8\ud2b9\ubcc4\uc2dc\uc7a5\u318d\uad11\uc5ed\uc2dc\uc7a5\u318d\ub3c4\uc9c0\uc0ac \ub610\ub294 \uc2dc\uc7a5\u318d\uad70\uc218\u318d\uc790\uce58\uad6c\uc758 \uad6c\uccad\uc7a5 \ub4f1 \uad00\uacc4 \ud589\uc815\uae30\uad00\uc758 \uc7a5\uc740 \uc218\ub3c4\uad8c\uc815\ube44\uacc4\ud68d\uc5d0 \ub9de\uc9c0 \uc544\ub2c8\ud558\ub294 \ud1a0\uc9c0 \uc774\uc6a9 \uacc4\ud68d\uc774\ub098 \uac1c\ubc1c \uacc4\ud68d \ub4f1\uc744 \uc218\ub9bd\u318d\uc2dc\ud589\ud558\uc5ec\uc11c\ub294 \uc544\ub2c8 \ub41c\ub2e4."}]}, {"@\uc870\ubb38\ud0a4": "0004001", "\uc870\ubb38\ubc88\ud638": "4", "\uc870\ubb38\uc5ec\ubd80": "\uc870\ubb38", "\uc870\ubb38\uc81c\ubaa9": "\uc218\ub3c4\uad8c\uc815\ube44\uacc4\ud68d\uc758 \uc218\ub9bd", "\uc870\ubb38\uc2dc\ud589\uc77c\uc790": "20180612", "\uc870\ubb38\uc774\ub3d9\uc774\uc804": "000000", "\uc870\ubb38\uc774\ub3d9\uc774\ud6c4": "000000", "\uc870\ubb38\ubcc0\uacbd\uc5ec\ubd80": null, "\uc870\ubb38\ub0b4\uc6a9": "\uc81c4\uc870(\uc218\ub3c4\uad8c\uc815\ube44\uacc4\ud68d\uc758 \uc218\ub9bd)", "\ud56d": [{"\ud56d\ubc88\ud638": "\u2460", "\ud56d\ub0b4\uc6a9": "\u2460 \uad6d\ud1a0\uad50\ud1b5\ubd80\uc7a5\uad00\uc740 \uc218\ub3c4\uad8c\uc758 \uc778\uad6c \ubc0f \uc0b0\uc5c5\uc758 \uc9d1\uc911\uc744 \uc5b5\uc81c\ud558\uace0 \uc801\uc815\ud558\uac8c \ubc30\uce58\ud558\uae30 \uc704\ud558\uc5ec \uc911\uc559\ud589\uc815\uae30\uad00\uc758 \uc7a5\uacfc \uc11c\uc6b8\ud2b9\ubcc4\uc2dc\uc7a5\u318d\uad11\uc5ed\uc2dc\uc7a5 \ub610\ub294 \ub3c4\uc9c0\uc0ac(\uc774\ud558 \"\uc2dc\u318d\ub3c4\uc9c0\uc0ac\"\ub77c \ud55c\ub2e4)\uc758 \uc758\uacac\uc744 \ub4e4\uc5b4 \ub2e4\uc74c \uac01 \ud638\uc758 \uc0ac\ud56d\uc774 \ud3ec\ud568\ub41c \uc218\ub3c4\uad8c\uc815\ube44\uacc4\ud68d\uc548\uc744 \uc785\uc548\ud55c\ub2e4. <\uac1c\uc815 2013.3.23>", "\ud638": [{"\ud638\ubc88\ud638": "1.", "\ud638\ub0b4\uc6a9": "1. \uc218\ub3c4\uad8c \uc815\ube44\uc758 \ubaa9\ud45c\uc640 \uae30\ubcf8 \ubc29\ud5a5\uc5d0 \uad00\ud55c \uc0ac\ud56d"}, {"\ud638\ubc88\ud638": "2.", "\ud638\ub0b4\uc6a9": "2. \uc778\uad6c\uc640 \uc0b0\uc5c5 \ub4f1\uc758 \ubc30\uce58\uc5d0 \uad00\ud55c \uc0ac\ud56d"}, {"\ud638\ubc88\ud638": "3.", "\ud638\ub0b4\uc6a9": "3. \uad8c\uc5ed(\u5708\u57df)\uc758 \uad6c\ubd84\uacfc \uad8c\uc5ed\ubcc4 \uc815\ube44\uc5d0 \uad00\ud55c \uc0ac\ud56d"}, {"\ud638\ubc88\ud638": "4.", "\ud638\ub0b4\uc6a9": "4. \uc778\uad6c\uc9d1\uc911\uc720\ubc1c\uc2dc\uc124 \ubc0f \uac1c\ubc1c\uc0ac\uc5c5\uc758 \uad00\ub9ac\uc5d0 \uad00\ud55c \uc0ac\ud56d"}, {"\ud638\ubc88\ud638": "5.", "\ud638\ub0b4\uc6a9": "5. \uad11\uc5ed\uc801 \uad50\ud1b5 \uc2dc\uc124\uacfc \uc0c1\ud558\uc218\ub3c4 \uc2dc\uc124 \ub4f1\uc758 \uc815\ube44\uc5d0 \uad00\ud55c \uc0ac\ud56d"}, {"\ud638\ubc88\ud638": "6.", "\ud638\ub0b4\uc6a9": "6. \ud658\uacbd \ubcf4\uc804\uc5d0 \uad00\ud55c \uc0ac\ud56d"}, {"\ud638\ubc88\ud638": "7.", "\ud638\ub0b4\uc6a9": "7. \uc218\ub3c4\uad8c \uc815\ube44\ub97c \uc704\ud55c \uc9c0\uc6d0 \ub4f1\uc5d0 \uad00\ud55c \uc0ac\ud56d"}, {"\ud638\ubc88\ud638": "8.", "\ud638\ub0b4\uc6a9": "8. \uc81c1\ud638\ubd80\ud130 \uc81c7\ud638\uae4c\uc9c0\uc758 \uc0ac\ud56d\uc5d0 \ub300\ud55c \uacc4\ud68d\uc758 \uc9d1\ud589 \ubc0f \uad00\ub9ac\uc5d0 \uad00\ud55c \uc0ac\ud56d"}, {"\ud638\ubc88\ud638": "9.", "\ud638\ub0b4\uc6a9": "9. \uadf8 \ubc16\uc5d0 \ub300\ud1b5\ub839\ub839\uc73c\ub85c \uc815\ud558\ub294 \uc218\ub3c4\uad8c \uc815\ube44\uc5d0 \uad00\ud55c \uc0ac\ud56d"}]}, {"\ud56d\ubc88\ud638": "\u2461", "\ud56d\ub0b4\uc6a9": "\u2461 \uad6d\ud1a0\uad50\ud1b5\ubd80\uc7a5\uad00\uc740 \uc81c1\ud56d\uc5d0 \ub530\ub978 \uc218\ub3c4\uad8c\uc815\ube44\uacc4\ud68d\uc548\uc744 \uc81c21\uc870\uc5d0 \ub530\ub978 \uc218\ub3c4\uad8c\uc815\ube44\uc704\uc6d0\ud68c\uc758 \uc2ec\uc758\ub97c \uac70\uce5c \ud6c4 \uad6d\ubb34\ud68c\uc758\uc758 \uc2ec\uc758\uc640 \ub300\ud1b5\ub839\uc758 \uc2b9\uc778\uc744 \ubc1b\uc544 \uacb0\uc815\ud55c\ub2e4. \uacb0\uc815\ub41c \uc218\ub3c4\uad8c\uc815\ube44\uacc4\ud68d\uc744 \ubcc0\uacbd\ud560 \ub54c\uc5d0\ub3c4 \ub610\ud55c \uac19\ub2e4. \ub2e4\ub9cc, \ub300\ud1b5\ub839\ub839\uc73c\ub85c \uc815\ud558\ub294 \uacbd\ubbf8\ud55c \uc0ac\ud56d\uc740 \uc218\ub3c4\uad8c\uc815\ube44\uc704\uc6d0\ud68c\uc758 \uc2ec\uc758\ub97c \uac70\uccd0 \ubcc0\uacbd\ud560 \uc218 \uc788\ub2e4. <\uac1c\uc815 2013.3.23>"}, {"\ud56d\ubc88\ud638": "\u2462", "\ud56d\ub0b4\uc6a9": "\u2462 \uad6d\ud1a0\uad50\ud1b5\ubd80\uc7a5\uad00\uc740 \uc81c2\ud56d\uc5d0 \ub530\ub77c \uacb0\uc815\ub41c \uc218\ub3c4\uad8c\uc815\ube44\uacc4\ud68d\uc744 \ub300\ud1b5\ub839\ub839\uc73c\ub85c \uc815\ud558\ub294 \ubc14\uc5d0 \ub530\ub77c \uace0\uc2dc\ud558\uace0, \uc911\uc559\ud589\uc815\uae30\uad00\uc758 \uc7a5 \ubc0f \uc2dc\u318d\ub3c4\uc9c0\uc0ac\uc5d0\uac8c \ud1b5\ubcf4\ud558\uc5ec\uc57c \ud55c\ub2e4. <\uac1c\uc815 2013.3.23>"}]}, {"@\uc870\ubb38\ud0a4": "0005001", "\uc870\ubb38\ubc88\ud638": "5", "\uc870\ubb38\uc5ec\ubd80": "\uc870\ubb38", "\uc870\ubb38\uc81c\ubaa9": "\ucd94\uc9c4 \uacc4\ud68d", "\uc870\ubb38\uc2dc\ud589\uc77c\uc790": "20180612", "\uc870\ubb38\uc774\ub3d9\uc774\uc804": "000000", "\uc870\ubb38\uc774\ub3d9\uc774\ud6c4": "000000", "\uc870\ubb38\ubcc0\uacbd\uc5ec\ubd80": null, "\uc870\ubb38\ub0b4\uc6a9": "\uc81c5\uc870(\ucd94\uc9c4 \uacc4\ud68d)", "\ud56d": [{"\ud56d\ubc88\ud638": "\u2460", "\ud56d\ub0b4\uc6a9": "\u2460 \uc911\uc559\ud589\uc815\uae30\uad00\uc758 \uc7a5 \ubc0f \uc2dc\u318d\ub3c4\uc9c0\uc0ac\ub294 \uc218\ub3c4\uad8c\uc815\ube44\uacc4\ud68d\uc744 \uc2e4\ud589\ud558\uae30 \uc704\ud55c \uc18c\uad00\ubcc4 \ucd94\uc9c4 \uacc4\ud68d\uc744 \uc218\ub9bd\ud558\uc5ec \uad6d\ud1a0\uad50\ud1b5\ubd80\uc7a5\uad00\uc5d0\uac8c \uc81c\ucd9c\ud558\uc5ec\uc57c \ud55c\ub2e4. <\uac1c\uc815 2013.3.23>"}, {"\ud56d\ubc88\ud638": "\u2461", "\ud56d\ub0b4\uc6a9": "\u2461 \uc81c1\ud56d\uc5d0 \ub530\ub978 \ucd94\uc9c4 \uacc4\ud68d\uc740 \uc218\ub3c4\uad8c\uc815\ube44\uc704\uc6d0\ud68c\uc758 \uc2ec\uc758\ub97c \uac70\uccd0 \ud655\uc815\ub418\uba70, \uad6d\ud1a0\uad50\ud1b5\ubd80\uc7a5\uad00\uc740 \ucd94\uc9c4 \uacc4\ud68d\uc774 \ud655\uc815\ub418\uba74 \uc911\uc559\ud589\uc815\uae30\uad00\uc758 \uc7a5 \ubc0f \uc2dc\u318d\ub3c4\uc9c0\uc0ac\uc5d0\uac8c \ud1b5\ubcf4\ud558\uc5ec\uc57c \ud55c\ub2e4. <\uac1c\uc815 2013.3.23>"}, {"\ud56d\ubc88\ud638": "\u2462", "\ud56d\ub0b4\uc6a9": "\u2462 \uc2dc\u318d\ub3c4\uc9c0\uc0ac\ub294 \ud655\uc815\ub41c \ucd94\uc9c4 \uacc4\ud68d\uc744 \ud1b5\ubcf4\ubc1b\uc73c\uba74 \uc9c0\uccb4 \uc5c6\uc774 \uace0\uc2dc\ud558\uc5ec\uc57c \ud55c\ub2e4."}, {"\ud56d\ubc88\ud638": "\u2463", "\ud56d\ub0b4\uc6a9": "\u2463 \uc911\uc559\ud589\uc815\uae30\uad00\uc758 \uc7a5 \ubc0f \uc2dc\u318d\ub3c4\uc9c0\uc0ac\ub294 \ucd94\uc9c4 \uacc4\ud68d\uc744 \uc9d1\ud589\ud55c \uc2e4\uc801\uc744 \ub300\ud1b5\ub839\ub839\uc73c\ub85c \uc815\ud558\ub294 \ubc14\uc5d0 \ub530\ub77c \uad6d\ud1a0\uad50\ud1b5\ubd80\uc7a5\uad00\uc5d0\uac8c \uc81c\ucd9c\ud558\uc5ec\uc57c \ud55c\ub2e4. <\uac1c\uc815 2011.5.19, 2013.3.23>"}]}, {"@\uc870\ubb38\ud0a4": "0006001", "\uc870\ubb38\ubc88\ud638": "6", "\uc870\ubb38\uc5ec\ubd80": "\uc870\ubb38", "\uc870\ubb38\uc81c\ubaa9": "\uad8c\uc5ed\uc758 \uad6c\ubd84\uacfc \uc9c0\uc815", "\uc870\ubb38\uc2dc\ud589\uc77c\uc790": "20180612", "\uc870\ubb38\uc774\ub3d9\uc774\uc804": "000000", "\uc870\ubb38\uc774\ub3d9\uc774\ud6c4": "000000", "\uc870\ubb38\ubcc0\uacbd\uc5ec\ubd80": null, "\uc870\ubb38\ub0b4\uc6a9": "\uc81c6\uc870(\uad8c\uc5ed\uc758 \uad6c\ubd84\uacfc \uc9c0\uc815)", "\ud56d": [{"\ud56d\ubc88\ud638": "\u2460", "\ud56d\ub0b4\uc6a9": "\u2460 \uc218\ub3c4\uad8c\uc758 \uc778\uad6c\uc640 \uc0b0\uc5c5\uc744 \uc801\uc815\ud558\uac8c \ubc30\uce58\ud558\uae30 \uc704\ud558\uc5ec \uc218\ub3c4\uad8c\uc744 \ub2e4\uc74c\uacfc \uac19\uc774 \uad6c\ubd84\ud55c\ub2e4.", "\ud638": [{"\ud638\ubc88\ud638": "1.", "\ud638\ub0b4\uc6a9": "1. \uacfc\ubc00\uc5b5\uc81c\uad8c\uc5ed: \uc778\uad6c\uc640 \uc0b0\uc5c5\uc774 \uc9c0\ub098\uce58\uac8c \uc9d1\uc911\ub418\uc5c8\uac70\ub098 \uc9d1\uc911\ub420 \uc6b0\ub824\uac00 \uc788\uc5b4 \uc774\uc804\ud558\uac70\ub098 \uc815\ube44\ud560 \ud544\uc694\uac00 \uc788\ub294 \uc9c0\uc5ed"}, {"\ud638\ubc88\ud638": "2.", "\ud638\ub0b4\uc6a9": "2. \uc131\uc7a5\uad00\ub9ac\uad8c\uc5ed: \uacfc\ubc00\uc5b5\uc81c\uad8c\uc5ed\uc73c\ub85c\ubd80\ud130 \uc774\uc804\ud558\ub294 \uc778\uad6c\uc640 \uc0b0\uc5c5\uc744 \uacc4\ud68d\uc801\uc73c\ub85c \uc720\uce58\ud558\uace0 \uc0b0\uc5c5\uc758 \uc785\uc9c0\uc640 \ub3c4\uc2dc\uc758 \uac1c\ubc1c\uc744 \uc801\uc815\ud558\uac8c \uad00\ub9ac\ud560 \ud544\uc694\uac00 \uc788\ub294 \uc9c0\uc5ed"}, {"\ud638\ubc88\ud638": "3.", "\ud638\ub0b4\uc6a9": "3. \uc790\uc5f0\ubcf4\uc804\uad8c\uc5ed: \ud55c\uac15 \uc218\uacc4\uc758 \uc218\uc9c8\uacfc \ub179\uc9c0 \ub4f1 \uc790\uc5f0\ud658\uacbd\uc744 \ubcf4\uc804\ud560 \ud544\uc694\uac00 \uc788\ub294 \uc9c0\uc5ed"}]}, {"\ud56d\ubc88\ud638": "\u2461", "\ud56d\ub0b4\uc6a9": "\u2461 \uacfc\ubc00\uc5b5\uc81c\uad8c\uc5ed, \uc131\uc7a5\uad00\ub9ac\uad8c\uc5ed \ubc0f \uc790\uc5f0\ubcf4\uc804\uad8c\uc5ed\uc758 \ubc94\uc704\ub294 \ub300\ud1b5\ub839\ub839\uc73c\ub85c \uc815\ud55c\ub2e4."}]}, {"@\uc870\ubb38\ud0a4": "0007001", "\uc870\ubb38\ubc88\ud638": "7", "\uc870\ubb38\uc5ec\ubd80": "\uc870\ubb38", "\uc870\ubb38\uc81c\ubaa9": "\uacfc\ubc00\uc5b5\uc81c\uad8c\uc5ed\uc758 \ud589\uc704 \uc81c\ud55c", "\uc870\ubb38\uc2dc\ud589\uc77c\uc790": "20180612", "\uc870\ubb38\uc774\ub3d9\uc774\uc804": "000000", "\uc870\ubb38\uc774\ub3d9\uc774\ud6c4": "000000", "\uc870\ubb38\ubcc0\uacbd\uc5ec\ubd80": null, "\uc870\ubb38\ub0b4\uc6a9": "\uc81c7\uc870(\uacfc\ubc00\uc5b5\uc81c\uad8c\uc5ed\uc758 \ud589\uc704 \uc81c\ud55c)", "\ud56d": [{"\ud56d\ubc88\ud638": "\u2460", "\ud56d\ub0b4\uc6a9": "\u2460 \uad00\uacc4 \ud589\uc815\uae30\uad00\uc758 \uc7a5\uc740 \uacfc\ubc00\uc5b5\uc81c\uad8c\uc5ed\uc5d0\uc11c \ub2e4\uc74c \uac01 \ud638\uc758 \ud589\uc704\ub098 \uadf8 \ud5c8\uac00\u318d\uc778\uac00\u318d\uc2b9\uc778 \ub610\ub294 \ud611\uc758 \ub4f1(\uc774\ud558 \"\ud5c8\uac00\ub4f1\"\uc774\ub77c \ud55c\ub2e4)\uc744 \ud558\uc5ec\uc11c\ub294 \uc544\ub2c8 \ub41c\ub2e4.", "\ud638": [{"\ud638\ubc88\ud638": "1.", "\ud638\ub0b4\uc6a9": "1. \ub300\ud1b5\ub839\ub839\uc73c\ub85c \uc815\ud558\ub294 \ud559\uad50, \uacf5\uacf5 \uccad\uc0ac, \uc5f0\uc218 \uc2dc\uc124, \uadf8 \ubc16\uc758 \uc778\uad6c\uc9d1\uc911\uc720\ubc1c\uc2dc\uc124\uc758 \uc2e0\uc124 \ub610\ub294 \uc99d\uc124(\uc6a9\ub3c4\ubcc0\uacbd\uc744 \ud3ec\ud568\ud558\uba70, \ud559\uad50\uc758 \uc99d\uc124\uc740 \uc785\ud559 \uc815\uc6d0\uc758 \uc99d\uc6d0\uc744 \ub9d0\ud55c\ub2e4. \uc774\ud558 \uac19\ub2e4)"}, {"\ud638\ubc88\ud638": "2.", "\ud638\ub0b4\uc6a9": "2. \uacf5\uc5c5\uc9c0\uc5ed\uc758 \uc9c0\uc815"}]}, {"\ud56d\ubc88\ud638": "\u2461", "\ud56d\ub0b4\uc6a9": "\u2461 \uad00\uacc4 \ud589\uc815\uae30\uad00\uc758 \uc7a5\uc740 \uad6d\ubbfc\uacbd\uc81c\uc758 \ubc1c\uc804\uacfc \uacf5\uacf5\ubcf5\ub9ac\uc758 \uc99d\uc9c4\uc744 \uc704\ud558\uc5ec \ud544\uc694\ud558\ub2e4\uace0 \uc778\uc815\ud558\uba74 \uc81c1\ud56d\uc5d0\ub3c4 \ubd88\uad6c\ud558\uace0 \ub2e4\uc74c \uac01 \ud638\uc758 \ud589\uc704\ub098 \uadf8 \ud5c8\uac00\ub4f1\uc744 \ud560 \uc218 \uc788\ub2e4. <\uac1c\uc815 2013.3.23>", "\ud638": [{"\ud638\ubc88\ud638": "1.", "\ud638\ub0b4\uc6a9": "1. \ub300\ud1b5\ub839\ub839\uc73c\ub85c \uc815\ud558\ub294 \ud559\uad50 \ub610\ub294 \uacf5\uacf5 \uccad\uc0ac\uc758 \uc2e0\uc124 \ub610\ub294 \uc99d\uc124"}, {"\ud638\ubc88\ud638": "2.", "\ud638\ub0b4\uc6a9": "2. \uc11c\uc6b8\ud2b9\ubcc4\uc2dc\u318d\uad11\uc5ed\uc2dc\u318d\ub3c4(\uc774\ud558 \"\uc2dc\u318d\ub3c4\"\ub77c \ud55c\ub2e4)\ubcc4 \uae30\uc874 \uacf5\uc5c5\uc9c0\uc5ed\uc758 \ucd1d\uba74\uc801\uc744 \uc99d\uac00\uc2dc\ud0a4\uc9c0 \uc544\ub2c8\ud558\ub294 \ubc94\uc704\uc5d0\uc11c\uc758 \uacf5\uc5c5\uc9c0\uc5ed \uc9c0\uc815. \ub2e4\ub9cc, \uad6d\ud1a0\uad50\ud1b5\ubd80\uc7a5\uad00\uc774 \uc218\ub3c4\uad8c\uc815\ube44\uc704\uc6d0\ud68c\uc758 \uc2ec\uc758\ub97c \uac70\uccd0 \uc9c0\uc815\ud558\uac70\ub098 \ud5c8\uac00\ub4f1\uc744 \ud558\ub294 \uacbd\uc6b0\uc5d0\ub9cc \ud574\ub2f9\ud55c\ub2e4."}]}]}, {"@\uc870\ubb38\ud0a4": "0008001", "\uc870\ubb38\ubc88\ud638": "8", "\uc870\ubb38\uc5ec\ubd80": "\uc870\ubb38", "\uc870\ubb38\uc81c\ubaa9": "\uc131\uc7a5\uad00\ub9ac\uad8c\uc5ed\uc758 \ud589\uc704 \uc81c\ud55c", "\uc870\ubb38\uc2dc\ud589\uc77c\uc790": "20180612", "\uc870\ubb38\uc774\ub3d9\uc774\uc804": "000000", "\uc870\ubb38\uc774\ub3d9\uc774\ud6c4": "000000", "\uc870\ubb38\ubcc0\uacbd\uc5ec\ubd80": null, "\uc870\ubb38\ub0b4\uc6a9": "\uc81c8\uc870(\uc131\uc7a5\uad00\ub9ac\uad8c\uc5ed\uc758 \ud589\uc704 \uc81c\ud55c)", "\ud56d": [{"\ud56d\ubc88\ud638": "\u2460", "\ud56d\ub0b4\uc6a9": "\u2460 \uad00\uacc4 \ud589\uc815\uae30\uad00\uc758 \uc7a5\uc740 \uc131\uc7a5\uad00\ub9ac\uad8c\uc5ed\uc774 \uc801\uc815\ud558\uac8c \uc131\uc7a5\ud558\ub3c4\ub85d \ud558\ub418, \uc9c0\ub098\uce5c \uc778\uad6c\uc9d1\uc911\uc744 \ucd08\ub798\ud558\uc9c0 \uc54a\ub3c4\ub85d \ub300\ud1b5\ub839\ub839\uc73c\ub85c \uc815\ud558\ub294 \ud559\uad50, \uacf5\uacf5 \uccad\uc0ac, \uc5f0\uc218 \uc2dc\uc124, \uadf8 \ubc16\uc758 \uc778\uad6c\uc9d1\uc911\uc720\ubc1c\uc2dc\uc124\uc758 \uc2e0\uc124\u318d\uc99d\uc124\uc774\ub098 \uadf8 \ud5c8\uac00\ub4f1\uc744 \ud558\uc5ec\uc11c\ub294 \uc544\ub2c8 \ub41c\ub2e4."}, {"\ud56d\ubc88\ud638": "\u2461", "\ud56d\ub0b4\uc6a9": "\u2461 \uad00\uacc4 \ud589\uc815\uae30\uad00\uc758 \uc7a5\uc740 \uc131\uc7a5\uad00\ub9ac\uad8c\uc5ed\uc5d0\uc11c \uacf5\uc5c5\uc9c0\uc5ed\uc744 \uc9c0\uc815\ud558\ub824\uba74 \ub300\ud1b5\ub839\ub839\uc73c\ub85c \uc815\ud558\ub294 \ubc94\uc704\uc5d0\uc11c \uc218\ub3c4\uad8c\uc815\ube44\uacc4\ud68d\uc73c\ub85c \uc815\ud558\ub294 \ubc14\uc5d0 \ub530\ub77c\uc57c \ud55c\ub2e4."}]}, {"@\uc870\ubb38\ud0a4": "0009001", "\uc870\ubb38\ubc88\ud638": "9", "\uc870\ubb38\uc5ec\ubd80": "\uc870\ubb38", "\uc870\ubb38\uc81c\ubaa9": "\uc790\uc5f0\ubcf4\uc804\uad8c\uc5ed\uc758 \ud589\uc704 \uc81c\ud55c", "\uc870\ubb38\uc2dc\ud589\uc77c\uc790": "20180612", "\uc870\ubb38\uc774\ub3d9\uc774\uc804": "000000", "\uc870\ubb38\uc774\ub3d9\uc774\ud6c4": "000000", "\uc870\ubb38\ubcc0\uacbd\uc5ec\ubd80": null, "\uc870\ubb38\ub0b4\uc6a9": "\uc81c9\uc870(\uc790\uc5f0\ubcf4\uc804\uad8c\uc5ed\uc758 \ud589\uc704 \uc81c\ud55c) \uad00\uacc4 \ud589\uc815\uae30\uad00\uc758 \uc7a5\uc740 \uc790\uc5f0\ubcf4\uc804\uad8c\uc5ed\uc5d0\uc11c\ub294 \ub2e4\uc74c \uac01 \ud638\uc758 \ud589\uc704\ub098 \uadf8 \ud5c8\uac00\ub4f1\uc744 \ud558\uc5ec\uc11c\ub294 \uc544\ub2c8 \ub41c\ub2e4. \ub2e4\ub9cc, \uad6d\ubbfc\uacbd\uc81c\uc758 \ubc1c\uc804\uacfc \uacf5\uacf5\ubcf5\ub9ac\uc758 \uc99d\uc9c4\uc744 \uc704\ud558\uc5ec \ud544\uc694\ud558\ub2e4\uace0 \uc778\uc815\ub418\ub294 \uacbd\uc6b0\ub85c\uc11c \ub300\ud1b5\ub839\ub839\uc73c\ub85c \uc815\ud558\ub294 \uacbd\uc6b0\uc5d0\ub294 \uadf8\ub7ec\ud558\uc9c0 \uc544\ub2c8\ud558\ub2e4.", "\ud56d": {"\ud638": [{"\ud638\ubc88\ud638": "1.", "\ud638\ub0b4\uc6a9": "1. \ud0dd\uc9c0, \uacf5\uc5c5 \uc6a9\uc9c0, \uad00\uad11\uc9c0 \ub4f1\uc758 \uc870\uc131\uc744 \ubaa9\uc801\uc73c\ub85c \ud558\ub294 \uc0ac\uc5c5\uc73c\ub85c\uc11c \ub300\ud1b5\ub839\ub839\uc73c\ub85c \uc815\ud558\ub294 \uc885\ub958 \ubc0f \uaddc\ubaa8 \uc774\uc0c1\uc758 \uac1c\ubc1c\uc0ac\uc5c5"}, {"\ud638\ubc88\ud638": "2.", "\ud638\ub0b4\uc6a9": "2. \ub300\ud1b5\ub839\ub839\uc73c\ub85c \uc815\ud558\ub294 \ud559\uad50, \uacf5\uacf5 \uccad\uc0ac, \uc5c5\ubb34\uc6a9 \uac74\ucd95\ubb3c, \ud310\ub9e4\uc6a9 \uac74\ucd95\ubb3c, \uc5f0\uc218 \uc2dc\uc124, \uadf8 \ubc16\uc758 \uc778\uad6c\uc9d1\uc911\uc720\ubc1c\uc2dc\uc124\uc758 \uc2e0\uc124 \ub610\ub294 \uc99d\uc124"}]}}, {"@\uc870\ubb38\ud0a4": "0010001", "\uc870\ubb38\ubc88\ud638": "10", "\uc870\ubb38\uc5ec\ubd80": "\uc870\ubb38", "\uc870\ubb38\uc81c\ubaa9": "\uc774\uc804\ud558\ub294 \uc790\uc5d0 \ub300\ud55c \uc9c0\uc6d0", "\uc870\ubb38\uc2dc\ud589\uc77c\uc790": "20180612", "\uc870\ubb38\uc774\ub3d9\uc774\uc804": "000000", "\uc870\ubb38\uc774\ub3d9\uc774\ud6c4": "000000", "\uc870\ubb38\ubcc0\uacbd\uc5ec\ubd80": null, "\uc870\ubb38\ub0b4\uc6a9": "\uc81c10\uc870(\uc774\uc804\ud558\ub294 \uc790\uc5d0 \ub300\ud55c \uc9c0\uc6d0) \uad6d\uac00, \uc9c0\ubc29\uc790\uce58\ub2e8\uccb4 \ub610\ub294 \u300c\uacf5\uacf5\uae30\uad00\uc758 \uc6b4\uc601\uc5d0 \uad00\ud55c \ubc95\ub960\u300d\uc5d0 \ub530\ub978 \uacf5\uacf5\uae30\uad00\uc740 \uacfc\ubc00\uc5b5\uc81c\uad8c\uc5ed\uc758 \uc778\uad6c\uc9d1\uc911\uc720\ubc1c\uc2dc\uc124\uc744 \uc131\uc7a5\uad00\ub9ac\uad8c\uc5ed\uc5d0 \uc870\uc131\ud55c \ub300\uc9c0(\u5788\u5730)\ub85c \uc774\uc804\ud558\ub824\ub294 \uc790\uc5d0\uac8c\ub294 \uadf8 \ub300\uc9c0\ub97c \uc6b0\uc120\ud558\uc5ec \ubd84\uc591\ud560 \uc218 \uc788\ub2e4."}, {"@\uc870\ubb38\ud0a4": "0011001", "\uc870\ubb38\ubc88\ud638": "11", "\uc870\ubb38\uc5ec\ubd80": "\uc870\ubb38", "\uc870\ubb38\uc81c\ubaa9": "\uc885\uc804 \ub300\uc9c0\uc5d0 \uad00\ud55c \uc870\uce58", "\uc870\ubb38\uc2dc\ud589\uc77c\uc790": "20180612", "\uc870\ubb38\uc774\ub3d9\uc774\uc804": "000000", "\uc870\ubb38\uc774\ub3d9\uc774\ud6c4": "000000", "\uc870\ubb38\ubcc0\uacbd\uc5ec\ubd80": null, "\uc870\ubb38\ub0b4\uc6a9": "\uc81c11\uc870(\uc885\uc804 \ub300\uc9c0\uc5d0 \uad00\ud55c \uc870\uce58)", "\ud56d": [{"\ud56d\ubc88\ud638": "\u2460", "\ud56d\ub0b4\uc6a9": "\u2460 \uad6d\ud1a0\uad50\ud1b5\ubd80\uc7a5\uad00 \ub610\ub294 \uc2dc\u318d\ub3c4\uc9c0\uc0ac\ub294 \uacfc\ubc00\uc5b5\uc81c\uad8c\uc5ed\uc758 \uc778\uad6c\uc9d1\uc911\uc720\ubc1c\uc2dc\uc124\uc774 \uc774\uc804\ub41c \uc885\uc804\uc758 \ub300\uc9c0(\uc774\ud558 \"\uc885\uc804\ub300\uc9c0\"\ub77c \ud55c\ub2e4)\ub97c \uc778\uad6c\uc9d1\uc911\uc720\ubc1c\uc2dc\uc124\uc758 \uc2e0\uc124 \ub610\ub294 \uc99d\uc124\uc774 \uc544\ub2cc \ub2e4\ub978 \uc6a9\ub3c4\ub85c \uc774\uc6a9\ud560 \uc218 \uc788\ub3c4\ub85d \ud558\uae30 \uc704\ud558\uc5ec \u300c\uad6d\ud1a0\uc758 \uacc4\ud68d \ubc0f \uc774\uc6a9\uc5d0 \uad00\ud55c \ubc95\ub960\u300d \ub4f1 \uad00\uacc4 \ubc95\ub960\uc5d0 \ub530\ub978 \uc9c0\uc5ed\uc758 \ubcc0\uacbd \ub4f1 \ud544\uc694\ud55c \uc870\uce58\ub97c \ud560 \uc218 \uc788\ub2e4. <\uac1c\uc815 2013.3.23>"}, {"\ud56d\ubc88\ud638": "\u2461", "\ud56d\ub0b4\uc6a9": "\u2461 \uad00\uacc4 \ud589\uc815\uae30\uad00\uc758 \uc7a5\uc740 \ub300\ud1b5\ub839\ub839\uc73c\ub85c \uc815\ud558\ub294 \uaddc\ubaa8 \uc774\uc0c1\uc758 \uc885\uc804\ub300\uc9c0\uc5d0 \uc778\uad6c\uc9d1\uc911\uc720\ubc1c\uc2dc\uc124\uc758 \uc2e0\uc124 \ub610\ub294 \uc99d\uc124\uc774\ub098 \uc774\uc758 \ud5c8\uac00\ub4f1\uc744 \ud558\ub824\uba74 \ubbf8\ub9ac \uc774\uc6a9 \uacc4\ud68d\uc744 \uc785\uc548\ud558\uc5ec \uc218\ub3c4\uad8c\uc815\ube44\uc704\uc6d0\ud68c\uc758 \uc2ec\uc758\ub97c \uac70\uccd0 \uad6d\ud1a0\uad50\ud1b5\ubd80\uc7a5\uad00\uacfc \ud611\uc758\ud558\uac70\ub098 \uc2b9\uc778\uc744 \ubc1b\uc544\uc57c \ud55c\ub2e4. <\uac1c\uc815 2013.3.23>"}]}, {"@\uc870\ubb38\ud0a4": "0012001", "\uc870\ubb38\ubc88\ud638": "12", "\uc870\ubb38\uc5ec\ubd80": "\uc870\ubb38", "\uc870\ubb38\uc81c\ubaa9": "\uacfc\ubc00\ubd80\ub2f4\uae08\uc758 \ubd80\uacfc\u318d\uc9d5\uc218", "\uc870\ubb38\uc2dc\ud589\uc77c\uc790": "20180612", "\uc870\ubb38\uc774\ub3d9\uc774\uc804": "000000", "\uc870\ubb38\uc774\ub3d9\uc774\ud6c4": "000000", "\uc870\ubb38\ubcc0\uacbd\uc5ec\ubd80": null, "\uc870\ubb38\ub0b4\uc6a9": "\uc81c12\uc870(\uacfc\ubc00\ubd80\ub2f4\uae08\uc758 \ubd80\uacfc\u318d\uc9d5\uc218)", "\ud56d": [{"\ud56d\ubc88\ud638": "\u2460", "\ud56d\ub0b4\uc6a9": "\u2460 \uacfc\ubc00\uc5b5\uc81c\uad8c\uc5ed\uc5d0 \uc18d\ud558\ub294 \uc9c0\uc5ed\uc73c\ub85c\uc11c \ub300\ud1b5\ub839\ub839\uc73c\ub85c \uc815\ud558\ub294 \uc9c0\uc5ed\uc5d0\uc11c \uc778\uad6c\uc9d1\uc911\uc720\ubc1c\uc2dc\uc124 \uc911 \uc5c5\ubb34\uc6a9 \uac74\ucd95\ubb3c, \ud310\ub9e4\uc6a9 \uac74\ucd95\ubb3c, \uacf5\uacf5 \uccad\uc0ac, \uadf8 \ubc16\uc5d0 \ub300\ud1b5\ub839\ub839\uc73c\ub85c \uc815\ud558\ub294 \uac74\ucd95\ubb3c\uc744 \uac74\ucd95(\uc2e0\ucd95\u318d\uc99d\ucd95 \ubc0f \uacf5\uacf5 \uccad\uc0ac\uac00 \uc544\ub2cc \uc2dc\uc124\uc744 \uacf5\uacf5 \uccad\uc0ac\ub85c \ud558\ub294 \uc6a9\ub3c4\ubcc0\uacbd, \uadf8 \ubc16\uc5d0 \ub300\ud1b5\ub839\ub839\uc73c\ub85c \uc815\ud558\ub294 \uc6a9\ub3c4\ubcc0\uacbd\uc744 \ub9d0\ud55c\ub2e4. \uc774\ud558 \uac19\ub2e4)\ud558\ub824\ub294 \uc790\ub294 \uacfc\ubc00\ubd80\ub2f4\uae08(\uc774\ud558 \"\ubd80\ub2f4\uae08\"\uc774\ub77c \ud55c\ub2e4)\uc744 \ub0b4\uc57c \ud55c\ub2e4."}, {"\ud56d\ubc88\ud638": "\u2461", "\ud56d\ub0b4\uc6a9": "\u2461 \ubd80\ub2f4\uae08\uc744 \ub0b4\uc57c \ud560 \uc790\uac00 \ub300\ud1b5\ub839\ub839\uc73c\ub85c \uc815\ud558\ub294 \uc870\ud569\uc778 \uacbd\uc6b0 \uadf8 \uc870\ud569\uc774 \ud574\uc0b0\ud558\uba74 \uadf8 \uc870\ud569\uc6d0\uc774 \ubd80\ub2f4\uae08\uc744 \ub0b4\uc57c \ud55c\ub2e4."}, {"\ud56d\ubc88\ud638": "\u2462", "\ud56d\ub0b4\uc6a9": "\u2462 \ubd80\ub2f4\uae08 \ub0a9\ubd80 \uc758\ubb34\uc758 \uc2b9\uacc4, \uc5f0\ub300(\uf99a\u5e36) \ub0a9\ubd80 \uc758\ubb34\uc640 \uc81c2\ucc28 \ub0a9\ubd80 \uc758\ubb34\uc5d0 \uad00\ud558\uc5ec\ub294 \u300c\uad6d\uc138\uae30\ubcf8\ubc95\u300d \uc81c23\uc870\ubd80\ud130 \uc81c25\uc870\uae4c\uc9c0 \ubc0f \uac19\uc740 \ubc95 \uc81c38\uc870\ubd80\ud130 \uc81c41\uc870\uae4c\uc9c0\uc758 \uaddc\uc815\uc744 \uc900\uc6a9\ud55c\ub2e4."}]}, {"@\uc870\ubb38\ud0a4": "0013001", "\uc870\ubb38\ubc88\ud638": "13", "\uc870\ubb38\uc5ec\ubd80": "\uc870\ubb38", "\uc870\ubb38\uc81c\ubaa9": "\ubd80\ub2f4\uae08\uc758 \uac10\uba74", "\uc870\ubb38\uc2dc\ud589\uc77c\uc790": "20180612", "\uc870\ubb38\uc774\ub3d9\uc774\uc804": "000000", "\uc870\ubb38\uc774\ub3d9\uc774\ud6c4": "000000", "\uc870\ubb38\ubcc0\uacbd\uc5ec\ubd80": null, "\uc870\ubb38\ub0b4\uc6a9": "\uc81c13\uc870(\ubd80\ub2f4\uae08\uc758 \uac10\uba74) \ub2e4\uc74c \uac01 \ud638\uc758 \uac74\ucd95\ubb3c\uc5d0 \ub300\ud558\uc5ec\ub294 \ub300\ud1b5\ub839\ub839\uc73c\ub85c \uc815\ud558\ub294 \ubc14\uc5d0 \ub530\ub77c \ubd80\ub2f4\uae08\uc744 \uac10\uba74\ud560 \uc218 \uc788\ub2e4. <\uac1c\uc815 2017.2.8>", "\ud56d": {"\ud638": [{"\ud638\ubc88\ud638": "1.", "\ud638\ub0b4\uc6a9": "1. \uad6d\uac00\ub098 \uc9c0\ubc29\uc790\uce58\ub2e8\uccb4\uac00 \uac74\ucd95\ud558\ub294 \uac74\ucd95\ubb3c"}, {"\ud638\ubc88\ud638": "2.", "\ud638\ub0b4\uc6a9": "2. \u300c\ub3c4\uc2dc \ubc0f \uc8fc\uac70\ud658\uacbd\uc815\ube44\ubc95\u300d\uc5d0 \ub530\ub978 \uc7ac\uac1c\ubc1c\uc0ac\uc5c5\uc5d0 \ub530\ub978 \uac74\ucd95\ubb3c"}, {"\ud638\ubc88\ud638": "3.", "\ud638\ub0b4\uc6a9": "3. \uac74\ucd95\ubb3c \uc911 \uc8fc\ucc28\uc7a5\uc774\ub098 \uadf8 \ubc16\uc5d0 \ub300\ud1b5\ub839\ub839\uc73c\ub85c \uc815\ud558\ub294 \uc6a9\ub3c4\ub85c \uc0ac\uc6a9\ub418\ub294 \uac74\ucd95\ubb3c"}, {"\ud638\ubc88\ud638": "4.", "\ud638\ub0b4\uc6a9": "4. \uac74\ucd95\ubb3c \uc911 \ub300\ud1b5\ub839\ub839\uc73c\ub85c \uc815\ud558\ub294 \uba74\uc801 \uc774\ud558\uc758 \ubd80\ubd84"}]}}, {"@\uc870\ubb38\ud0a4": "0014001", "\uc870\ubb38\ubc88\ud638": "14", "\uc870\ubb38\uc5ec\ubd80": "\uc870\ubb38", "\uc870\ubb38\uc81c\ubaa9": "\ubd80\ub2f4\uae08\uc758 \uc0b0\uc815 \uae30\uc900", "\uc870\ubb38\uc2dc\ud589\uc77c\uc790": "20180612", "\uc870\ubb38\uc774\ub3d9\uc774\uc804": "000000", "\uc870\ubb38\uc774\ub3d9\uc774\ud6c4": "000000", "\uc870\ubb38\ubcc0\uacbd\uc5ec\ubd80": null, "\uc870\ubb38\ub0b4\uc6a9": "\uc81c14\uc870(\ubd80\ub2f4\uae08\uc758 \uc0b0\uc815 \uae30\uc900)", "\ud56d": [{"\ud56d\ubc88\ud638": "\u2460", "\ud56d\ub0b4\uc6a9": "\u2460 \ubd80\ub2f4\uae08\uc740 \uac74\ucd95\ube44\uc758 100\ubd84\uc758 10\uc73c\ub85c \ud558\ub418, \uc9c0\uc5ed\ubcc4 \uc5ec\uac74 \ub4f1\uc744 \uace0\ub824\ud558\uc5ec \ub300\ud1b5\ub839\ub839\uc73c\ub85c \uc815\ud558\ub294 \ubc14\uc5d0 \ub530\ub77c \uac74\ucd95\ube44\uc758 100\ubd84\uc758 5\uae4c\uc9c0 \uc870\uc815(\u8abf\u6574)\ud560 \uc218 \uc788\ub2e4."}, {"\ud56d\ubc88\ud638": "\u2461", "\ud56d\ub0b4\uc6a9": "\u2461 \uc81c1\ud56d\uc5d0 \ub530\ub978 \uac74\ucd95\ube44\ub294 \uad6d\ud1a0\uad50\ud1b5\ubd80\uc7a5\uad00\uc774 \uace0\uc2dc\ud558\ub294 \ud45c\uc900\uac74\ucd95\ube44\ub97c \uae30\uc900\uc73c\ub85c \uc0b0\uc815\ud55c\ub2e4. <\uac1c\uc815 2013.3.23>"}, {"\ud56d\ubc88\ud638": "\u2462", "\ud56d\ub0b4\uc6a9": "\u2462 \ubd80\ub2f4\uae08\uc758 \uc0b0\uc815\uc5d0 \uad00\ud55c \uad6c\uccb4\uc801\uc778 \uc0ac\ud56d\uc740 \ub300\ud1b5\ub839\ub839\uc73c\ub85c \uc815\ud55c\ub2e4."}]}, {"@\uc870\ubb38\ud0a4": "0015001", "\uc870\ubb38\ubc88\ud638": "15", "\uc870\ubb38\uc5ec\ubd80": "\uc870\ubb38", "\uc870\ubb38\uc81c\ubaa9": "\ubd80\ub2f4\uae08\uc758 \ubd80\uacfc\u318d\uc9d5\uc218 \ubc0f \ub0a9\ubd80 \uae30\ud55c \ub4f1", "\uc870\ubb38\uc2dc\ud589\uc77c\uc790": "20180612", "\uc870\ubb38\uc774\ub3d9\uc774\uc804": "000000", "\uc870\ubb38\uc774\ub3d9\uc774\ud6c4": "000000", "\uc870\ubb38\ubcc0\uacbd\uc5ec\ubd80": null, "\uc870\ubb38\ub0b4\uc6a9": "\uc81c15\uc870(\ubd80\ub2f4\uae08\uc758 \ubd80\uacfc\u318d\uc9d5\uc218 \ubc0f \ub0a9\ubd80 \uae30\ud55c \ub4f1)", "\ud56d": [{"\ud56d\ubc88\ud638": "\u2460", "\ud56d\ub0b4\uc6a9": "\u2460 \ubd80\ub2f4\uae08\uc740 \ubd80\uacfc \ub300\uc0c1 \uac74\ucd95\ubb3c\uc774 \uc18d\ud55c \uc9c0\uc5ed\uc744 \uad00\ud560\ud558\ub294 \uc2dc\u318d\ub3c4\uc9c0\uc0ac\uac00 \ubd80\uacfc\u318d\uc9d5\uc218\ud558\ub418, \uac74\ucd95\ubb3c\uc758 \uac74\ucd95 \ud5c8\uac00\uc77c, \uac74\ucd95 \uc2e0\uace0\uc77c \ub610\ub294 \uc6a9\ub3c4\ubcc0\uacbd\uc77c\uc744 \uae30\uc900\uc73c\ub85c \uc0b0\uc815\ud558\uc5ec \ubd80\uacfc\ud55c\ub2e4."}, {"\ud56d\ubc88\ud638": "\u2461", "\ud56d\ub0b4\uc6a9": "\u2461 \ubd80\ub2f4\uae08\uc758 \ub0a9\ubd80 \uae30\ud55c\uc740 \uac74\ucd95\ubb3c\uc758 \uc0ac\uc6a9\uc2b9\uc778\uc77c(\uc784\uc2dc \uc0ac\uc6a9\uc2b9\uc778\uc744 \ubc1b\uc740 \uacbd\uc6b0\uc5d0\ub294 \uc784\uc2dc \uc0ac\uc6a9\uc2b9\uc778\uc77c\uc744 \ub9d0\ud55c\ub2e4)\ub85c \ud558\ub418, \uc0ac\uc6a9\uc2b9\uc778\uc774 \ud544\uc694 \uc5c6\ub294 \uacbd\uc6b0\uc5d0\ub294 \ubd80\uacfc\uc77c\ubd80\ud130 6\uac1c\uc6d4\ub85c \ud55c\ub2e4."}, {"\ud56d\ubc88\ud638": "\u2462", "\ud56d\ub0b4\uc6a9": "\u2462 \uc2dc\u318d\ub3c4\uc9c0\uc0ac\ub294 \ub0a9\ubd80 \uc758\ubb34\uc790\uac00 \ubd80\ub2f4\uae08\uc744 \ub0a9\ubd80 \uae30\ud55c\uae4c\uc9c0 \ub0b4\uc9c0 \uc544\ub2c8\ud558\uba74 \ub0a9\ubd80 \uae30\ud55c\uc774 \uc9c0\ub09c \ud6c4 10\uc77c \uc774\ub0b4\uc5d0 \ub3c5\ucd09\uc7a5\uc744 \ubc1c\ubd80\ud558\uc5ec\uc57c \ud558\uba70, \uc774 \uacbd\uc6b0\uc758 \ub0a9\ubd80 \uae30\ud55c\uc740 \ub3c5\ucd09\uc7a5 \ubc1c\ubd80\uc77c\ubd80\ud130 10\uc77c\ub85c \ud55c\ub2e4."}, {"\ud56d\ubc88\ud638": "\u2463", "\ud56d\ub0b4\uc6a9": "\u2463 \uc2dc\u318d\ub3c4\uc9c0\uc0ac\ub294 \ub0a9\ubd80 \uc758\ubb34\uc790\uac00 \ub0a9\ubd80 \uae30\ud55c\uae4c\uc9c0 \ubd80\ub2f4\uae08\uc744 \ub0b4\uc9c0 \uc544\ub2c8\ud558\uba74 \u300c\uad6d\uc138\uc9d5\uc218\ubc95\u300d \uc81c21\uc870\ub97c \uc900\uc6a9\ud558\uc5ec \uac00\uc0b0\uae08\uc744 \uc9d5\uc218\ud55c\ub2e4. <\uac1c\uc815 2017.1.17>"}, {"\ud56d\ubc88\ud638": "\u2464", "\ud56d\ub0b4\uc6a9": "\u2464 \uc2dc\u318d\ub3c4\uc9c0\uc0ac\ub294 \ub0a9\ubd80 \uc758\ubb34\uc790\uac00 \ub3c5\ucd09\uc7a5\uc744 \ubc1b\uace0\ub3c4 \uc9c0\uc815\ub41c \uae30\ud55c\uae4c\uc9c0 \ubd80\ub2f4\uae08\uacfc \uac00\uc0b0\uae08\uc744 \ub0b4\uc9c0 \uc544\ub2c8\ud558\uba74 \u300c\uc9c0\ubc29\uc138\uc678\uc218\uc785\uae08\uc758 \uc9d5\uc218 \ub4f1\uc5d0 \uad00\ud55c \ubc95\ub960\u300d\uc5d0 \ub530\ub77c \uc9d5\uc218\ud560 \uc218 \uc788\ub2e4. <\uac1c\uc815 2013.8.6>"}, {"\ud56d\ubc88\ud638": "\u2465", "\ud56d\ub0b4\uc6a9": "\u2465 \uacfc\uc624\ub0a9(\u904e\u8aa4\u7d0d)\ub41c \ubd80\ub2f4\uae08\u318d\uac00\uc0b0\uae08 \ubc0f \uccb4\ub0a9\ucc98\ubd84\ube44\uc758 \ucc98\ub9ac\uc5d0 \uad00\ud558\uc5ec\ub294 \u300c\uc9c0\ubc29\uc138\uae30\ubcf8\ubc95\u300d\uc744 \uc900\uc6a9\ud558\uba70, \uadf8 \ubc16\uc5d0 \ubd80\ub2f4\uae08\uc758 \ubd80\uacfc\u318d\uc9d5\uc218\u318d\ub0a9\ubd80\uc758 \ubc29\ubc95\u318d\uc808\ucc28 \ub4f1\uc5d0 \uad00\ud558\uc5ec \ud544\uc694\ud55c \uc0ac\ud56d\uc740 \ub300\ud1b5\ub839\ub839\uc73c\ub85c \uc815\ud55c\ub2e4. <\uac1c\uc815 2010.3.31, 2017.1.17>"}]}, {"@\uc870\ubb38\ud0a4": "0016001", "\uc870\ubb38\ubc88\ud638": "16", "\uc870\ubb38\uc5ec\ubd80": "\uc870\ubb38", "\uc870\ubb38\uc81c\ubaa9": "\ubd80\ub2f4\uae08\uc758 \ubc30\ubd84", "\uc870\ubb38\uc2dc\ud589\uc77c\uc790": "20180612", "\uc870\ubb38\uc774\ub3d9\uc774\uc804": "000000", "\uc870\ubb38\uc774\ub3d9\uc774\ud6c4": "000000", "\uc870\ubb38\ubcc0\uacbd\uc5ec\ubd80": null, "\uc870\ubb38\ub0b4\uc6a9": "\uc81c16\uc870(\ubd80\ub2f4\uae08\uc758 \ubc30\ubd84) \uc9d5\uc218\ub41c \ubd80\ub2f4\uae08\uc758 100\ubd84\uc758 50\uc740 \u300c\uad6d\uac00\uade0\ud615\ubc1c\uc804 \ud2b9\ubcc4\ubc95\u300d\uc5d0 \ub530\ub978 \uad6d\uac00\uade0\ud615\ubc1c\uc804\ud2b9\ubcc4\ud68c\uacc4\uc5d0 \uadc0\uc18d\ud558\uace0, 100\ubd84\uc758 50\uc740 \ubd80\ub2f4\uae08\uc744 \uc9d5\uc218\ud55c \uac74\ucd95\ubb3c\uc774 \uc788\ub294 \uc2dc\u318d\ub3c4\uc5d0 \uadc0\uc18d\ud55c\ub2e4. <\uac1c\uc815 2009.4.22, 2014.1.7, 2018.3.20>"}, {"@\uc870\ubb38\ud0a4": "0017001", "\uc870\ubb38\ubc88\ud638": "17", "\uc870\ubb38\uc5ec\ubd80": "\uc870\ubb38", "\uc870\ubb38\uc81c\ubaa9": "\uc774\uc758\uc2e0\uccad", "\uc870\ubb38\uc2dc\ud589\uc77c\uc790": "20180612", "\uc870\ubb38\uc774\ub3d9\uc774\uc804": "000000", "\uc870\ubb38\uc774\ub3d9\uc774\ud6c4": "000000", "\uc870\ubb38\ubcc0\uacbd\uc5ec\ubd80": null, "\uc870\ubb38\ub0b4\uc6a9": "\uc81c17\uc870(\uc774\uc758\uc2e0\uccad)", "\ud56d": [{"\ud56d\ubc88\ud638": "\u2460", "\ud56d\ub0b4\uc6a9": "\u2460 \ubd80\ub2f4\uae08\uc758 \ubd80\uacfc\u318d\uc9d5\uc218\uc5d0 \uc774\uc758\uac00 \uc788\ub294 \uc790\ub294 \u300c\uacf5\uc775\uc0ac\uc5c5\uc744 \uc704\ud55c \ud1a0\uc9c0 \ub4f1\uc758 \ucde8\ub4dd \ubc0f \ubcf4\uc0c1\uc5d0 \uad00\ud55c \ubc95\ub960\u300d\uc5d0 \ub530\ub978 \uc911\uc559\ud1a0\uc9c0\uc218\uc6a9\uc704\uc6d0\ud68c\uc5d0 \ud589\uc815\uc2ec\ud310\uc744 \uccad\uad6c\ud560 \uc218 \uc788\ub2e4."}, {"\ud56d\ubc88\ud638": "\u2461", "\ud56d\ub0b4\uc6a9": "\u2461 \uc81c1\ud56d\uc758 \ud589\uc815\uc2ec\ud310\uccad\uad6c\uc5d0 \ub300\ud558\uc5ec\ub294 \u300c\ud589\uc815\uc2ec\ud310\ubc95\u300d \uc81c6\uc870\uc5d0\ub3c4 \ubd88\uad6c\ud558\uace0 \uc911\uc559\ud1a0\uc9c0\uc218\uc6a9\uc704\uc6d0\ud68c\uac00 \uc2ec\ub9ac\u318d\uc758\uacb0\ud558\uc5ec \uc7ac\uacb0(\u88c1\u6c7a)\ud55c\ub2e4. <\uac1c\uc815 2010.1.25>"}]}, {"@\uc870\ubb38\ud0a4": "0018001", "\uc870\ubb38\ubc88\ud638": "18", "\uc870\ubb38\uc5ec\ubd80": "\uc870\ubb38", "\uc870\ubb38\uc81c\ubaa9": "\ucd1d\ub7c9\uaddc\uc81c", "\uc870\ubb38\uc2dc\ud589\uc77c\uc790": "20180612", "\uc870\ubb38\uc774\ub3d9\uc774\uc804": "000000", "\uc870\ubb38\uc774\ub3d9\uc774\ud6c4": "000000", "\uc870\ubb38\ubcc0\uacbd\uc5ec\ubd80": "Y", "\uc870\ubb38\ub0b4\uc6a9": "\uc81c18\uc870(\ucd1d\ub7c9\uaddc\uc81c)", "\ud56d": [{"\ud56d\ubc88\ud638": "\u2460", "\ud56d\uc81c\uac1c\uc815\uc720\ud615": "\uc2e0\uc124", "\ud56d\uc81c\uac1c\uc815\uc77c\uc790\ubb38\uc790\uc5f4": "\uac1c\uc815 2013.3.23, 2018.6.12", "\ud56d\ub0b4\uc6a9": "\u2460 \uad6d\ud1a0\uad50\ud1b5\ubd80\uc7a5\uad00\uc740 \uacf5\uc7a5, \ud559\uad50, \uadf8 \ubc16\uc5d0 \ub300\ud1b5\ub839\ub839\uc73c\ub85c \uc815\ud558\ub294 \uc778\uad6c\uc9d1\uc911\uc720\ubc1c\uc2dc\uc124\uc774 \uc218\ub3c4\uad8c\uc5d0 \uc9c0\ub098\uce58\uac8c \uc9d1\uc911\ub418\uc9c0 \uc544\ub2c8\ud558\ub3c4\ub85d \ud558\uae30 \uc704\ud558\uc5ec \uadf8 \uc2e0\uc124 \ub610\ub294 \uc99d\uc124\uc758 \ucd1d\ud5c8\uc6a9\ub7c9(\u7e3d\u8a31\u5bb9\u91cf)\uc744 \uc815\ud558\uc5ec \uc774\ub97c \ucd08\uacfc\ud558\ub294 \uc2e0\uc124 \ub610\ub294 \uc99d\uc124\uc744 \uc81c\ud55c\ud560 \uc218 \uc788\ub2e4. \uc774 \uacbd\uc6b0 \uad6d\ud1a0\uad50\ud1b5\ubd80\uc7a5\uad00\uc740 \ucd1d\ud5c8\uc6a9\ub7c9\uacfc \uadf8 \uc0b0\ucd9c \uadfc\uac70\ub97c \uace0\uc2dc\ud558\uc5ec\uc57c \ud55c\ub2e4. <\uac1c\uc815 2013.3.23, 2018.6.12>"}, {"\ud56d\ubc88\ud638": "\u2461", "\ud56d\ub0b4\uc6a9": "\u2461 \uacf5\uc7a5\uc5d0 \ub300\ud55c \uc81c1\ud56d\uc758 \ucd1d\ub7c9\uaddc\uc81c\uc758 \ub0b4\uc6a9\uacfc \ubc29\ubc95\uc740 \ub300\ud1b5\ub839\ub839\uc73c\ub85c \uc815\ud558\ub294 \ubc14\uc5d0 \ub530\ub77c \uc218\ub3c4\uad8c\uc815\ube44\uc704\uc6d0\ud68c\uc758 \uc2ec\uc758\ub97c \uac70\uccd0 \uacb0\uc815\ud558\uba70, \uad6d\ud1a0\uad50\ud1b5\ubd80\uc7a5\uad00\uc740 \uc774\ub97c \uace0\uc2dc\ud558\uc5ec\uc57c \ud55c\ub2e4. <\uac1c\uc815 2013.3.23>"}, {"\ud56d\ubc88\ud638": "\u2462", "\ud56d\ub0b4\uc6a9": "\u2462 \ud559\uad50\ub098 \uadf8 \ubc16\uc5d0 \ub300\ud1b5\ub839\ub839\uc73c\ub85c \uc815\ud558\ub294 \uc778\uad6c\uc9d1\uc911\uc720\ubc1c\uc2dc\uc124\uc5d0 \ub300\ud55c \uc81c1\ud56d\uc758 \ucd1d\ub7c9\uaddc\uc81c\uc758 \ub0b4\uc6a9\uc740 \ub300\ud1b5\ub839\ub839\uc73c\ub85c \uc815\ud55c\ub2e4."}, {"\ud56d\ubc88\ud638": "\u2463", "\ud56d\ub0b4\uc6a9": "\u2463 \uad00\uacc4 \ud589\uc815\uae30\uad00\uc758 \uc7a5\uc740 \uc778\uad6c\uc9d1\uc911\uc720\ubc1c\uc2dc\uc124\uc758 \uc2e0\uc124 \ub610\ub294 \uc99d\uc124\uc5d0 \ub300\ud558\uc5ec \uc81c2\ud56d\uacfc \uc81c3\ud56d\uc5d0 \ub530\ub978 \ucd1d\ub7c9\uaddc\uc81c\uc758 \ub0b4\uc6a9\uacfc \ub2e4\ub974\uac8c \ud5c8\uac00\ub4f1\uc744 \ud558\uc5ec\uc11c\ub294 \uc544\ub2c8 \ub41c\ub2e4."}]}, {"@\uc870\ubb38\ud0a4": "0019001", "\uc870\ubb38\ubc88\ud638": "19", "\uc870\ubb38\uc5ec\ubd80": "\uc870\ubb38", "\uc870\ubb38\uc81c\ubaa9": "\ub300\uaddc\ubaa8\uac1c\ubc1c\uc0ac\uc5c5\uc5d0 \ub300\ud55c \uaddc\uc81c", "\uc870\ubb38\uc2dc\ud589\uc77c\uc790": "20180612", "\uc870\ubb38\uc774\ub3d9\uc774\uc804": "000000", "\uc870\ubb38\uc774\ub3d9\uc774\ud6c4": "000000", "\uc870\ubb38\ubcc0\uacbd\uc5ec\ubd80": null, "\uc870\ubb38\ub0b4\uc6a9": "\uc81c19\uc870(\ub300\uaddc\ubaa8\uac1c\ubc1c\uc0ac\uc5c5\uc5d0 \ub300\ud55c \uaddc\uc81c)", "\ud56d": [{"\ud56d\ubc88\ud638": "\u2460", "\ud56d\ub0b4\uc6a9": "\u2460 \uad00\uacc4 \ud589\uc815\uae30\uad00\uc758 \uc7a5\uc740 \uc218\ub3c4\uad8c\uc5d0\uc11c \ub300\uaddc\ubaa8\uac1c\ubc1c\uc0ac\uc5c5\uc744 \uc2dc\ud589\ud558\uac70\ub098 \uadf8 \ud5c8\uac00\ub4f1\uc744 \ud558\ub824\uba74 \uadf8 \uac1c\ubc1c \uacc4\ud68d\uc744 \uc218\ub3c4\uad8c\uc815\ube44\uc704\uc6d0\ud68c\uc758 \uc2ec\uc758\ub97c \uac70\uccd0 \uad6d\ud1a0\uad50\ud1b5\ubd80\uc7a5\uad00\uacfc \ud611\uc758\ud558\uac70\ub098 \uc2b9\uc778\uc744 \ubc1b\uc544\uc57c \ud55c\ub2e4. \uad6d\ud1a0\uad50\ud1b5\ubd80\uc7a5\uad00\uc774 \ub300\uaddc\ubaa8\uac1c\ubc1c\uc0ac\uc5c5\uc744 \uc2dc\ud589\ud558\uac70\ub098 \uadf8 \ud5c8\uac00\ub4f1\uc744 \ud558\ub824\ub294 \uacbd\uc6b0\uc5d0\ub3c4 \ub610\ud55c \uac19\ub2e4. <\uac1c\uc815 2013.3.23>"}, {"\ud56d\ubc88\ud638": "\u2461", "\ud56d\ub0b4\uc6a9": "\u2461 \uad00\uacc4 \ud589\uc815\uae30\uad00\uc758 \uc7a5\uc774 \uc81c1\ud56d\uc5d0 \ub530\ub978 \uc218\ub3c4\uad8c\uc815\ube44\uc704\uc6d0\ud68c\uc758 \uc2ec\uc758\ub97c \uc694\uccad\ud558\ub294 \uacbd\uc6b0\uc5d0 \uad50\ud1b5 \ubb38\uc81c, \ud658\uacbd\uc624\uc5fc \ubb38\uc81c \ubc0f \uc778\uad6c\uc9d1\uc911 \ubb38\uc81c \ub4f1\uc744 \ubc29\uc9c0\ud558\uae30 \uc704\ud55c \ubc29\uc548\uacfc \ub300\ud1b5\ub839\ub839\uc73c\ub85c \uc815\ud558\ub294 \uad11\uc5ed\uc801 \uae30\ubc18 \uc2dc\uc124\uc758 \uc124\uce58 \uacc4\ud68d\uc744 \uac01\uac01 \uc218\ub9bd\ud558\uc5ec \ud568\uaed8 \uc81c\ucd9c\ud558\uc5ec\uc57c \ud55c\ub2e4. <\uac1c\uc815 2011.5.19>"}, {"\ud56d\ubc88\ud638": "\u2462", "\ud56d\ub0b4\uc6a9": "\u2462 \uc81c2\ud56d\uc5d0 \ub530\ub978 \uad50\ud1b5 \ubb38\uc81c \ubc0f \ud658\uacbd\uc624\uc5fc \ubb38\uc81c\ub97c \ubc29\uc9c0\ud558\uae30 \uc704\ud55c \ubc29\uc548\uc740 \uac01\uac01 \u300c\ub3c4\uc2dc\uad50\ud1b5\uc815\ube44 \ucd09\uc9c4\ubc95\u300d\uacfc \u300c\ud658\uacbd\uc601\ud5a5\ud3c9\uac00\ubc95\u300d\uc5d0\uc11c \uc815\ud558\ub294 \ubc14\uc5d0 \ub530\ub974\uace0, \uc778\uad6c\uc9d1\uc911 \ubb38\uc81c\ub97c \ubc29\uc9c0\ud558\uae30 \uc704\ud55c \uc778\uad6c\uc720\ubc1c\ud6a8\uacfc \ubd84\uc11d, \uc800\uac10\ubc29\uc548 \uc218\ub9bd \ub4f1\uc5d0 \ud544\uc694\ud55c \uc0ac\ud56d\uc740 \ub300\ud1b5\ub839\ub839\uc73c\ub85c \uc815\ud558\ub294 \ubc14\uc5d0 \ub530\ub978\ub2e4. <\uac1c\uc815 2011.5.19>"}]}, {"@\uc870\ubb38\ud0a4": "0020001", "\uc870\ubb38\ubc88\ud638": "20", "\uc870\ubb38\uc5ec\ubd80": "\uc870\ubb38", "\uc870\ubb38\uc81c\ubaa9": "\uad11\uc5ed\uc801 \uae30\ubc18 \uc2dc\uc124\uc758 \uc124\uce58\ube44\uc6a9 \ubd80\ub2f4", "\uc870\ubb38\uc2dc\ud589\uc77c\uc790": "20180612", "\uc870\ubb38\uc774\ub3d9\uc774\uc804": "000000", "\uc870\ubb38\uc774\ub3d9\uc774\ud6c4": "000000", "\uc870\ubb38\ubcc0\uacbd\uc5ec\ubd80": null, "\uc870\ubb38\ub0b4\uc6a9": "\uc81c20\uc870(\uad11\uc5ed\uc801 \uae30\ubc18 \uc2dc\uc124\uc758 \uc124\uce58\ube44\uc6a9 \ubd80\ub2f4) \uc81c19\uc870\uc81c2\ud56d\uc5d0 \ub530\ub978 \uad11\uc5ed\uc801 \uae30\ubc18 \uc2dc\uc124\uc758 \uc124\uce58\ube44\uc6a9\uc740 \uc218\ub3c4\uad8c\uc815\ube44\uc704\uc6d0\ud68c\uc758 \uc2ec\uc758\ub97c \uac70\uccd0 \ub300\uaddc\ubaa8\uac1c\ubc1c\uc0ac\uc5c5\uc744 \uc2dc\ud589\ud558\ub294 \uc790\uc5d0\uac8c \ubd80\ub2f4\uc2dc\ud0ac \uc218 \uc788\ub2e4."}, {"@\uc870\ubb38\ud0a4": "0021001", "\uc870\ubb38\ubc88\ud638": "21", "\uc870\ubb38\uc5ec\ubd80": "\uc870\ubb38", "\uc870\ubb38\uc81c\ubaa9": "\uc218\ub3c4\uad8c\uc815\ube44\uc704\uc6d0\ud68c\uc758 \uc124\uce58 \ub4f1", "\uc870\ubb38\uc2dc\ud589\uc77c\uc790": "20180612", "\uc870\ubb38\uc774\ub3d9\uc774\uc804": "000000", "\uc870\ubb38\uc774\ub3d9\uc774\ud6c4": "000000", "\uc870\ubb38\ubcc0\uacbd\uc5ec\ubd80": null, "\uc870\ubb38\ub0b4\uc6a9": "\uc81c21\uc870(\uc218\ub3c4\uad8c\uc815\ube44\uc704\uc6d0\ud68c\uc758 \uc124\uce58 \ub4f1)", "\ud56d": [{"\ud56d\ubc88\ud638": "\u2460", "\ud56d\ub0b4\uc6a9": "\u2460 \uc218\ub3c4\uad8c\uc758 \uc815\ube44 \ubc0f \uac74\uc804\ud55c \ubc1c\uc804\uacfc \uad00\ub828\ub418\ub294 \uc911\uc694 \uc815\ucc45\uc744 \uc2ec\uc758\ud558\uae30 \uc704\ud558\uc5ec \uad6d\ud1a0\uad50\ud1b5\ubd80\uc7a5\uad00 \uc18c\uc18d\uc73c\ub85c \uc218\ub3c4\uad8c\uc815\ube44\uc704\uc6d0\ud68c(\uc774\ud558 \"\uc704\uc6d0\ud68c\"\ub77c \ud55c\ub2e4)\ub97c \ub454\ub2e4. <\uac1c\uc815 2011.5.19, 2013.3.23>"}, {"\ud56d\ubc88\ud638": "\u2461", "\ud56d\ub0b4\uc6a9": "\u2461 \uc704\uc6d0\ud68c\ub294 \ub2e4\uc74c \uac01 \ud638\uc758 \uc0ac\ud56d\uc744 \uc2ec\uc758\ud55c\ub2e4.", "\ud638": [{"\ud638\ubc88\ud638": "1.", "\ud638\ub0b4\uc6a9": "1. \uc218\ub3c4\uad8c\uc815\ube44\uacc4\ud68d\uc758 \uc218\ub9bd\uacfc \ubcc0\uacbd\uc5d0 \uad00\ud55c \uc0ac\ud56d"}, {"\ud638\ubc88\ud638": "2.", "\ud638\ub0b4\uc6a9": "2. \uc218\ub3c4\uad8c\uc815\ube44\uacc4\ud68d\uc758 \uc18c\uad00\ubcc4 \ucd94\uc9c4 \uacc4\ud68d\uc5d0 \uad00\ud55c \uc0ac\ud56d"}, {"\ud638\ubc88\ud638": "3.", "\ud638\ub0b4\uc6a9": "3. \uc218\ub3c4\uad8c\uc758 \uc815\ube44\uc640 \uad00\ub828\ub41c \uc815\ucc45\uacfc \uacc4\ud68d\uc758 \uc870\uc815\uc5d0 \uad00\ud55c \uc0ac\ud56d"}, {"\ud638\ubc88\ud638": "4.", "\ud638\ub0b4\uc6a9": "4. \uacfc\ubc00\uc5b5\uc81c\uad8c\uc5ed\uc5d0\uc11c \ucd94\uc9c4\ub420 \uacf5\uc5c5\uc9c0\uc5ed\uc758 \uc9c0\uc815\uc5d0 \uad00\ud55c \uc0ac\ud56d"}, {"\ud638\ubc88\ud638": "5.", "\ud638\ub0b4\uc6a9": "5. \uc885\uc804\ub300\uc9c0\uc758 \uc774\uc6a9 \uacc4\ud68d\uc5d0 \uad00\ud55c \uc0ac\ud56d"}, {"\ud638\ubc88\ud638": "6.", "\ud638\ub0b4\uc6a9": "6. \uc81c18\uc870\uc5d0 \ub530\ub978 \ucd1d\ub7c9\uaddc\uc81c\uc5d0 \uad00\ud55c \uc0ac\ud56d"}, {"\ud638\ubc88\ud638": "7.", "\ud638\ub0b4\uc6a9": "7. \ub300\uaddc\ubaa8\uac1c\ubc1c\uc0ac\uc5c5\uc758 \uac1c\ubc1c \uacc4\ud68d\uc5d0 \uad00\ud55c \uc0ac\ud56d"}, {"\ud638\ubc88\ud638": "8.", "\ud638\ub0b4\uc6a9": "8. \uadf8 \ubc16\uc5d0 \uc218\ub3c4\uad8c\uc758 \uc815\ube44\uc5d0 \ud544\uc694\ud55c \uc0ac\ud56d\uc73c\ub85c\uc11c \ub300\ud1b5\ub839\ub839\uc73c\ub85c \uc815\ud558\ub294 \uc0ac\ud56d"}]}]}, {"@\uc870\ubb38\ud0a4": "0022001", "\uc870\ubb38\ubc88\ud638": "22", "\uc870\ubb38\uc5ec\ubd80": "\uc870\ubb38", "\uc870\ubb38\uc81c\ubaa9": "\uad6c\uc131", "\uc870\ubb38\uc2dc\ud589\uc77c\uc790": "20180612", "\uc870\ubb38\uc774\ub3d9\uc774\uc804": "000000", "\uc870\ubb38\uc774\ub3d9\uc774\ud6c4": "000000", "\uc870\ubb38\ubcc0\uacbd\uc5ec\ubd80": null, "\uc870\ubb38\ub0b4\uc6a9": "\uc81c22\uc870(\uad6c\uc131)", "\ud56d": [{"\ud56d\ubc88\ud638": "\u2460", "\ud56d\ub0b4\uc6a9": "\u2460 \uc704\uc6d0\ud68c\ub294 \uc704\uc6d0\uc7a5\uc744 \ud3ec\ud568\ud55c 20\uba85 \uc774\ub0b4\uc758 \uc704\uc6d0\uc73c\ub85c \uad6c\uc131\ud55c\ub2e4."}, {"\ud56d\ubc88\ud638": "\u2461", "\ud56d\ub0b4\uc6a9": "\u2461 \uc704\uc6d0\uc7a5\uc740 \uad6d\ud1a0\uad50\ud1b5\ubd80\uc7a5\uad00\uc774 \ub41c\ub2e4. <\uac1c\uc815 2013.3.23>"}, {"\ud56d\ubc88\ud638": "\u2462", "\ud56d\ub0b4\uc6a9": "\u2462 \uc704\uc6d0\ud68c\uc758 \uc704\uc6d0\uc740 \ub2e4\uc74c \uac01 \ud638\uc758 \uc0ac\ub78c\uc73c\ub85c \ud558\ub418, \uc81c3\ud638\uc5d0 \ud574\ub2f9\ud558\ub294 \uc0ac\ub78c\uc774 5\uba85 \uc774\uc0c1\uc774\uc5b4\uc57c \ud55c\ub2e4. <\uac1c\uc815 2013.3.23>", "\ud638": [{"\ud638\ubc88\ud638": "1.", "\ud638\ub0b4\uc6a9": "1. \ub300\ud1b5\ub839\ub839\uc73c\ub85c \uc815\ud558\ub294 \uad00\uacc4 \uc911\uc559\ud589\uc815\uae30\uad00\uc758 \ucc28\uad00"}, {"\ud638\ubc88\ud638": "2.", "\ud638\ub0b4\uc6a9": "2. \ub300\ud1b5\ub839\ub839\uc73c\ub85c \uc815\ud558\ub294 \uc2dc\u318d\ub3c4\uc758 \ubd80\uc2dc\uc7a5 \ub610\ub294 \ubd80\uc9c0\uc0ac"}, {"\ud638\ubc88\ud638": "3.", "\ud638\ub0b4\uc6a9": "3. \uc218\ub3c4\uad8c \uc815\ucc45\uc5d0 \uad00\ud55c \ud559\uc2dd\uacfc \uacbd\ud5d8\uc774 \ud48d\ubd80\ud55c \uc0ac\ub78c \uc911\uc5d0\uc11c \uad6d\ud1a0\uad50\ud1b5\ubd80\uc7a5\uad00\uc774 \uc704\ucd09\ud558\ub294 \uc0ac\ub78c"}]}, {"\ud56d\ubc88\ud638": "\u2463", "\ud56d\ub0b4\uc6a9": "\u2463 \uc81c3\ud56d\uc81c3\ud638\uc5d0 \ud574\ub2f9\ud558\ub294 \uc704\uc6d0(\uc774\ud558 \"\uc704\ucd09\uc704\uc6d0\"\uc774\ub77c \ud55c\ub2e4)\uc758 \uc784\uae30\ub294 2\ub144\uc73c\ub85c \ud558\uba70, \uc5f0\uc784\ud560 \uc218 \uc788\ub2e4."}], "\uc870\ubb38\ucc38\uace0\uc790\ub8cc": "[\uc804\ubb38\uac1c\uc815 2011.5.19]"}, {"@\uc870\ubb38\ud0a4": "0022021", "\uc870\ubb38\ubc88\ud638": "22", "\uc870\ubb38\uac00\uc9c0\ubc88\ud638": "2", "\uc870\ubb38\uc5ec\ubd80": "\uc870\ubb38", "\uc870\ubb38\uc81c\ubaa9": "\uc704\ucd09\uc704\uc6d0\uc758 \uacb0\uaca9\uc0ac\uc720", "\uc870\ubb38\uc2dc\ud589\uc77c\uc790": "20180612", "\uc870\ubb38\uc774\ub3d9\uc774\uc804": "000000", "\uc870\ubb38\uc774\ub3d9\uc774\ud6c4": "000000", "\uc870\ubb38\ubcc0\uacbd\uc5ec\ubd80": null, "\uc870\ubb38\ub0b4\uc6a9": "\uc81c22\uc870\uc7582(\uc704\ucd09\uc704\uc6d0\uc758 \uacb0\uaca9\uc0ac\uc720)", "\ud56d": [{"\ud56d\ubc88\ud638": "\u2460", "\ud56d\ub0b4\uc6a9": "\u2460 \ub2e4\uc74c \uac01 \ud638\uc758 \uc5b4\ub290 \ud558\ub098\uc5d0 \ud574\ub2f9\ud558\ub294 \uc0ac\ub78c\uc740 \uc704\ucd09\uc704\uc6d0\uc774 \ub420 \uc218 \uc5c6\ub2e4. <\uac1c\uc815 2017.1.17>", "\ud638": [{"\ud638\ubc88\ud638": "1.", "\ud638\ub0b4\uc6a9": "1. \ud53c\uc131\ub144\ud6c4\uacac\uc778 \ub610\ub294 \ud53c\ud55c\uc815\ud6c4\uacac\uc778"}, {"\ud638\ubc88\ud638": "2.", "\ud638\ub0b4\uc6a9": "2. \ud30c\uc0b0\uc120\uace0\ub97c \ubc1b\uace0 \ubcf5\uad8c\ub418\uc9c0 \uc544\ub2c8\ud55c \uc0ac\ub78c"}, {"\ud638\ubc88\ud638": "3.", "\ud638\ub0b4\uc6a9": "3. \uae08\uace0 \uc774\uc0c1\uc758 \uc2e4\ud615\uc744 \uc120\uace0\ubc1b\uace0 \uadf8 \uc9d1\ud589\uc774 \ub05d\ub098\uac70\ub098(\uc9d1\ud589\uc774 \ub05d\ub09c \uac83\uc73c\ub85c \ubcf4\ub294 \uacbd\uc6b0\ub97c \ud3ec\ud568\ud55c\ub2e4) \uc9d1\ud589\uc774 \uba74\uc81c\ub41c \ub0a0\ubd80\ud130 2\ub144\uc774 \uc9c0\ub098\uc9c0 \uc544\ub2c8\ud55c \uc0ac\ub78c"}, {"\ud638\ubc88\ud638": "4.", "\ud638\ub0b4\uc6a9": "4. \uae08\uace0 \uc774\uc0c1\uc758 \ud615\uc758 \uc9d1\ud589\uc720\uc608 \uc120\uace0\ub97c \ubc1b\uace0 \uadf8 \uc720\uc608\uae30\uac04 \uc911\uc5d0 \uc788\ub294 \uc0ac\ub78c"}]}, {"\ud56d\ubc88\ud638": "\u2461", "\ud56d\ub0b4\uc6a9": "\u2461 \uc704\ucd09\uc704\uc6d0\uc774 \uc81c1\ud56d \uac01 \ud638\uc758 \uc5b4\ub290 \ud558\ub098\uc5d0 \ud574\ub2f9\ud558\uac8c \ub418\ub294 \uacbd\uc6b0 \uc704\uc6d0\uc790\uaca9\uc744 \uc783\ub294\ub2e4."}], "\uc870\ubb38\ucc38\uace0\uc790\ub8cc": "[\ubcf8\uc870\uc2e0\uc124 2011.5.19]"}, {"@\uc870\ubb38\ud0a4": "0022031", "\uc870\ubb38\ubc88\ud638": "22", "\uc870\ubb38\uac00\uc9c0\ubc88\ud638": "3", "\uc870\ubb38\uc5ec\ubd80": "\uc870\ubb38", "\uc870\ubb38\uc81c\ubaa9": "\ubc8c\uce59 \uc801\uc6a9 \uc2dc\uc758 \uacf5\ubb34\uc6d0 \uc758\uc81c", "\uc870\ubb38\uc2dc\ud589\uc77c\uc790": "20180612", "\uc870\ubb38\uc774\ub3d9\uc774\uc804": "000000", "\uc870\ubb38\uc774\ub3d9\uc774\ud6c4": "000000", "\uc870\ubb38\ubcc0\uacbd\uc5ec\ubd80": null, "\uc870\ubb38\ub0b4\uc6a9": "\uc81c22\uc870\uc7583(\ubc8c\uce59 \uc801\uc6a9 \uc2dc\uc758 \uacf5\ubb34\uc6d0 \uc758\uc81c) \uc704\uc6d0\ud68c\uc758 \uc704\ucd09\uc704\uc6d0\uc740 \u300c\ud615\ubc95\u300d \uc81c127\uc870, \uc81c129\uc870\ubd80\ud130 \uc81c132\uc870\uae4c\uc9c0\uc758 \uaddc\uc815\uc744 \uc801\uc6a9\ud560 \ub54c\uc5d0\ub294 \uacf5\ubb34\uc6d0\uc73c\ub85c \ubcf8\ub2e4.", "\uc870\ubb38\ucc38\uace0\uc790\ub8cc": "[\ubcf8\uc870\uc2e0\uc124 2011.5.19]"}, {"@\uc870\ubb38\ud0a4": "0023001", "\uc870\ubb38\ubc88\ud638": "23", "\uc870\ubb38\uc5ec\ubd80": "\uc870\ubb38", "\uc870\ubb38\uc81c\ubaa9": "\uc218\ub3c4\uad8c\uc815\ube44\uc2e4\ubb34\uc704\uc6d0\ud68c\uc758 \uc124\uce58 \ub4f1", "\uc870\ubb38\uc2dc\ud589\uc77c\uc790": "20180612", "\uc870\ubb38\uc774\ub3d9\uc774\uc804": "000000", "\uc870\ubb38\uc774\ub3d9\uc774\ud6c4": "000000", "\uc870\ubb38\ubcc0\uacbd\uc5ec\ubd80": null, "\uc870\ubb38\ub0b4\uc6a9": "\uc81c23\uc870(\uc218\ub3c4\uad8c\uc815\ube44\uc2e4\ubb34\uc704\uc6d0\ud68c\uc758 \uc124\uce58 \ub4f1)", "\ud56d": [{"\ud56d\ubc88\ud638": "\u2460", "\ud56d\ub0b4\uc6a9": "\u2460 \uc704\uc6d0\ud68c\uc5d0 \uad00\uacc4 \ud589\uc815\uae30\uad00\uc758 \uacf5\ubb34\uc6d0\uacfc \uc218\ub3c4\uad8c \uc815\ube44 \uc815\ucc45\uc5d0 \uad00\uacc4\ub418\ub294 \ubd84\uc57c\uc5d0 \ud559\uc2dd\uacfc \uacbd\ud5d8\uc774 \ud48d\ubd80\ud55c \uc790\ub85c \uad6c\uc131\ub418\ub294 \uc218\ub3c4\uad8c\uc815\ube44\uc2e4\ubb34\uc704\uc6d0\ud68c\ub97c \ub454\ub2e4."}, {"\ud56d\ubc88\ud638": "\u2461", "\ud56d\ub0b4\uc6a9": "\u2461 \uc218\ub3c4\uad8c\uc815\ube44\uc2e4\ubb34\uc704\uc6d0\ud68c\ub294 \ub2e4\uc74c\uc758 \uc0ac\ud56d\uc744 \uc2ec\uc758\ud55c\ub2e4. <\uac1c\uc815 2011.5.19>", "\ud638": [{"\ud638\ubc88\ud638": "1.", "\ud638\ub0b4\uc6a9": "1. \uc704\uc6d0\ud68c\uc5d0\uc11c \uc2ec\uc758\ud560 \uc548\uac74\uc5d0 \ub300\ud55c \uac80\ud1a0\u318d\uc870\uc815"}, {"\ud638\ubc88\ud638": "2.", "\ud638\ub0b4\uc6a9": "2. \ub300\ud1b5\ub839\ub839\uc73c\ub85c \uc815\ud558\ub294 \ubc14\uc5d0 \ub530\ub77c \uc704\uc6d0\ud68c\ub85c\ubd80\ud130 \uc704\uc784\ubc1b\uc740 \uc0ac\ud56d"}]}]}, {"@\uc870\ubb38\ud0a4": "0023021", "\uc870\ubb38\ubc88\ud638": "23", "\uc870\ubb38\uac00\uc9c0\ubc88\ud638": "2", "\uc870\ubb38\uc5ec\ubd80": "\uc870\ubb38", "\uc870\ubb38\uc81c\ubaa9": "\ud68c\uc758\ub85d\uc758 \uc791\uc131\u318d\ubcf4\uc874 \ubc0f \uacf5\uac1c", "\uc870\ubb38\uc2dc\ud589\uc77c\uc790": "20180612", "\uc870\ubb38\uc774\ub3d9\uc774\uc804": "000000", "\uc870\ubb38\uc774\ub3d9\uc774\ud6c4": "000000", "\uc870\ubb38\ubcc0\uacbd\uc5ec\ubd80": null, "\uc870\ubb38\ub0b4\uc6a9": "\uc81c23\uc870\uc7582(\ud68c\uc758\ub85d\uc758 \uc791\uc131\u318d\ubcf4\uc874 \ubc0f \uacf5\uac1c)", "\ud56d": [{"\ud56d\ubc88\ud638": "\u2460", "\ud56d\ub0b4\uc6a9": "\u2460 \uc704\uc6d0\ud68c\uc640 \uc218\ub3c4\uad8c\uc815\ube44\uc2e4\ubb34\uc704\uc6d0\ud68c\ub294 \ub2e4\uc74c \uac01 \ud638\uc758 \uc0ac\ud56d\uc744 \uc801\uc740 \ud68c\uc758\ub85d\uc744 \uc791\uc131\u318d\ubcf4\uc874\ud558\uc5ec\uc57c \ud55c\ub2e4. \ub2e4\ub9cc, \uc11c\uba74\uc2ec\uc758\uc758 \uacbd\uc6b0\uc5d0\ub294 \ud68c\uc758\ub85d\uc744 \uc11c\uba74\uc758\uacb0\uc11c\ub85c \uac08\uc74c\ud55c\ub2e4.", "\ud638": [{"\ud638\ubc88\ud638": "1.", "\ud638\ub0b4\uc6a9": "1. \ud68c\uc758 \uc77c\uc2dc \ubc0f \uc7a5\uc18c"}, {"\ud638\ubc88\ud638": "2.", "\ud638\ub0b4\uc6a9": "2. \ucd9c\uc11d\uc704\uc6d0"}, {"\ud638\ubc88\ud638": "3.", "\ud638\ub0b4\uc6a9": "3. \uc2ec\uc758\ub0b4\uc6a9 \ubc0f \uc758\uacb0\uc0ac\ud56d"}]}, {"\ud56d\ubc88\ud638": "\u2461", "\ud56d\ub0b4\uc6a9": "\u2461 \uc81c1\ud56d\uc5d0 \ub530\ub978 \ud68c\uc758\ub85d\uc740 \uacf5\uac1c\ud558\uc5ec\uc57c \ud55c\ub2e4. \ub2e4\ub9cc, \u300c\uacf5\uacf5\uae30\uad00\uc758 \uc815\ubcf4\uacf5\uac1c\uc5d0 \uad00\ud55c \ubc95\ub960\u300d \uc81c9\uc870\uc81c1\ud56d\uc5d0 \ub530\ub978 \ube44\uacf5\uac1c \ub300\uc0c1 \uc815\ubcf4\ub294 \uacf5\uac1c\ud558\uc9c0 \uc544\ub2c8\ud560 \uc218 \uc788\ub2e4."}], "\uc870\ubb38\ucc38\uace0\uc790\ub8cc": "[\ubcf8\uc870\uc2e0\uc124 2017.1.17]"}, {"@\uc870\ubb38\ud0a4": "0024001", "\uc870\ubb38\ubc88\ud638": "24", "\uc870\ubb38\uc5ec\ubd80": "\uc870\ubb38", "\uc870\ubb38\uc81c\ubaa9": "\uc704\uc6d0\ud68c \ub4f1\uc758 \uc870\uc9c1 \ub4f1", "\uc870\ubb38\uc2dc\ud589\uc77c\uc790": "20180612", "\uc870\ubb38\uc774\ub3d9\uc774\uc804": "000000", "\uc870\ubb38\uc774\ub3d9\uc774\ud6c4": "000000", "\uc870\ubb38\ubcc0\uacbd\uc5ec\ubd80": null, "\uc870\ubb38\ub0b4\uc6a9": "\uc81c24\uc870(\uc704\uc6d0\ud68c \ub4f1\uc758 \uc870\uc9c1 \ub4f1) \uc774 \ubc95\uc73c\ub85c \uaddc\uc815\ud55c \uc0ac\ud56d \uc678\uc5d0 \uc704\uc6d0\ud68c\uc640 \uc218\ub3c4\uad8c\uc815\ube44\uc2e4\ubb34\uc704\uc6d0\ud68c\uc758 \uc870\uc9c1\uacfc \uc6b4\uc601 \ub4f1\uc5d0 \ud544\uc694\ud55c \uc0ac\ud56d\uc740 \ub300\ud1b5\ub839\ub839\uc73c\ub85c \uc815\ud55c\ub2e4."}, {"@\uc870\ubb38\ud0a4": "0025001", "\uc870\ubb38\ubc88\ud638": "25", "\uc870\ubb38\uc5ec\ubd80": "\uc870\ubb38", "\uc870\ubb38\uc81c\ubaa9": "\uae30\ucd08\uc870\uc0ac \ub4f1", "\uc870\ubb38\uc2dc\ud589\uc77c\uc790": "20180612", "\uc870\ubb38\uc774\ub3d9\uc774\uc804": "000000", "\uc870\ubb38\uc774\ub3d9\uc774\ud6c4": "000000", "\uc870\ubb38\ubcc0\uacbd\uc5ec\ubd80": null, "\uc870\ubb38\ub0b4\uc6a9": "\uc81c25\uc870(\uae30\ucd08\uc870\uc0ac \ub4f1) \uad6d\ud1a0\uad50\ud1b5\ubd80\uc7a5\uad00\uc740 \uc218\ub3c4\uad8c\uc815\ube44\uacc4\ud68d\uc744 \uc218\ub9bd \ub610\ub294 \ubcc0\uacbd\ud558\uac70\ub098 \ud6a8\uc728\uc801\uc73c\ub85c \ucd94\uc9c4\ud558\ub294 \ub370\uc5d0 \ud544\uc694\ud558\uba74 \uc778\uad6c, \uc0b0\uc5c5, \ud1a0\uc9c0 \uc774\uc6a9, \uc8fc\uc694 \uc2dc\uc124 \ubc0f \uae30\ubc18 \uc2dc\uc124 \ub4f1\uc5d0 \uad00\ud55c \uae30\ucd08\uc870\uc0ac\ub97c \uc2e4\uc2dc\ud558\uac70\ub098 \uad00\uacc4 \ud589\uc815\uae30\uad00\uc758 \uc7a5\uc5d0\uac8c \ud544\uc694\ud55c \uc790\ub8cc\ub97c \uc81c\ucd9c\ud558\uac70\ub098 \uc9c0\uc6d0\ud558\ub3c4\ub85d \uc694\uccad\ud560 \uc218 \uc788\ub2e4. <\uac1c\uc815 2013.3.23>"}, {"@\uc870\ubb38\ud0a4": "0026001", "\uc870\ubb38\ubc88\ud638": "26", "\uc870\ubb38\uc5ec\ubd80": "\uc870\ubb38", "\uc870\ubb38\uc81c\ubaa9": "\ubcf4\uace0\uc640 \uac10\ub3c5", "\uc870\ubb38\uc2dc\ud589\uc77c\uc790": "20180612", "\uc870\ubb38\uc774\ub3d9\uc774\uc804": "000000", "\uc870\ubb38\uc774\ub3d9\uc774\ud6c4": "000000", "\uc870\ubb38\ubcc0\uacbd\uc5ec\ubd80": null, "\uc870\ubb38\ub0b4\uc6a9": "\uc81c26\uc870(\ubcf4\uace0\uc640 \uac10\ub3c5)", "\ud56d": [{"\ud56d\ubc88\ud638": "\u2460", "\ud56d\ub0b4\uc6a9": "\u2460 \uad6d\ud1a0\uad50\ud1b5\ubd80\uc7a5\uad00\uc740 \uc218\ub3c4\uad8c\uc815\ube44\uacc4\ud68d\uc744 \ud6a8\uc728\uc801\uc73c\ub85c \ucd94\uc9c4\ud558\ub294 \ub370\uc5d0 \ud544\uc694\ud558\ub2e4\uace0 \uc778\uc815\ud558\uba74 \uc2dc\u318d\ub3c4\uc9c0\uc0ac\uc5d0\uac8c \ubcf4\uace0\ub098 \uc790\ub8cc \uc81c\ucd9c\uc744 \uba85\ud560 \uc218 \uc788\uc73c\uba70, \uc18c\uc18d \uacf5\ubb34\uc6d0\uc5d0\uac8c \uc5c5\ubb34 \uc9d1\ud589 \uc0c1\ud669\uc774\ub098 \uc9c0\uc5ed \ud604\ud669\uc744 \uac80\uc0ac\ud558\uac70\ub098 \uc870\uc0ac\ud558\uac8c \ud560 \uc218 \uc788\ub2e4. <\uac1c\uc815 2013.3.23>"}, {"\ud56d\ubc88\ud638": "\u2461", "\ud56d\ub0b4\uc6a9": "\u2461 \uc81c1\ud56d\uc5d0 \ub530\ub77c \uc5c5\ubb34 \uc9d1\ud589 \uc0c1\ud669\uc774\ub098 \uc9c0\uc5ed \ud604\ud669\uc744 \uac80\uc0ac\ud558\uac70\ub098 \uc870\uc0ac\ud558\ub294 \uacf5\ubb34\uc6d0\uc740 \uadf8 \uad8c\ud55c\uc744 \ud45c\uc2dc\ud558\ub294 \uc99d\ud45c\ub97c \uc9c0\ub2c8\uace0 \uc774\ub97c \uad00\uacc4\uc778\uc5d0\uac8c \ub0b4\ubcf4\uc5ec\uc57c \ud55c\ub2e4."}]}, {"@\uc870\ubb38\ud0a4": "0027001", "\uc870\ubb38\ubc88\ud638": "27", "\uc870\ubb38\uc5ec\ubd80": "\uc870\ubb38", "\uc870\ubb38\uc81c\ubaa9": "\uad8c\ud55c\uc758 \uc704\uc784", "\uc870\ubb38\uc2dc\ud589\uc77c\uc790": "20180612", "\uc870\ubb38\uc774\ub3d9\uc774\uc804": "000000", "\uc870\ubb38\uc774\ub3d9\uc774\ud6c4": "000000", "\uc870\ubb38\ubcc0\uacbd\uc5ec\ubd80": null, "\uc870\ubb38\ub0b4\uc6a9": "\uc81c27\uc870(\uad8c\ud55c\uc758 \uc704\uc784) \uad6d\ud1a0\uad50\ud1b5\ubd80\uc7a5\uad00\uc740 \uc774 \ubc95\uc5d0 \ub530\ub978 \uad8c\ud55c\uc758 \uc77c\ubd80\ub97c \ub300\ud1b5\ub839\ub839\uc73c\ub85c \uc815\ud558\ub294 \ubc14\uc5d0 \ub530\ub77c \uc2dc\u318d\ub3c4\uc9c0\uc0ac\uc5d0\uac8c \uc704\uc784\ud560 \uc218 \uc788\ub2e4. <\uac1c\uc815 2013.3.23>"}]}, "\ubd80\uce59": {"\ubd80\uce59\ub2e8\uc704": [{"@\ubd80\uce59\ud0a4": "2008032108977", "\ubd80\uce59\uacf5\ud3ec\uc77c\uc790": "20080321", "\ubd80\uce59\uacf5\ud3ec\ubc88\ud638": "08977", "\ubd80\uce59\ub0b4\uc6a9": "\ubd80\uce59 <\uc81c8977\ud638,2008.3.21>\n\n\n\u2460(\uc2dc\ud589\uc77c) \uc774 \ubc95\uc740 \uacf5\ud3ec\ud55c \ub0a0\ubd80\ud130 \uc2dc\ud589\ud55c\ub2e4.\n\n\n\u2461(\uacfc\ubc00\ubd80\ub2f4\uae08 \ubd80\uacfc\uc5d0 \uad00\ud55c \uacbd\uacfc\uc870\uce58) \ubc95\ub960 \uc81c4721\ud638 \uc218\ub3c4\uad8c\uc815\ube44\uacc4\ud68d\ubc95\uac1c\uc815\ubc95\ub960\uc758 \uc2dc\ud589\uc77c\uc778 1994\ub144 4\uc6d4 8\uc77c \ub2f9\uc2dc \uc885\uc804\uc758 \uaddc\uc815\uc5d0 \ub530\ub77c \uc218\ub3c4\uad8c\uc815\ube44\uc2ec\uc758\uc704\uc6d0\ud68c\uc758 \uc2ec\uc758\ub97c \uac70\uccd0 \uac74\uc124\ubd80\uc7a5\uad00\uc774 \ud611\uc758 \ub610\ub294 \uc2b9\uc778\ud55c \uac74\ucd95\ubb3c\uacfc \uac74\ucd95\ubb3c\uc758 \uac74\ucd95\uc5d0 \uad00\ud55c \ud5c8\uac00\ub4f1\uc744 \uc2e0\uccad\ud55c \uac74\ucd95\ubb3c\uc5d0 \ub300\ud558\uc5ec\ub294 \uc81c12\uc870\uc758 \uac1c\uc815\uaddc\uc815\uc5d0 \ub530\ub978 \uacfc\ubc00\ubd80\ub2f4\uae08\uc744 \ubd80\uacfc\ud558\uc9c0 \uc544\ub2c8\ud55c\ub2e4.\n\n\n\u2462(\ucc98\ubd84 \ub4f1\uc5d0 \uad00\ud55c \uc77c\ubc18\uc801 \uacbd\uacfc\uc870\uce58) \uc774 \ubc95 \uc2dc\ud589 \ub2f9\uc2dc \uc885\uc804\uc758 \uaddc\uc815\uc5d0 \ub530\ub978 \ud589\uc815\uae30\uad00\uc758 \ud589\uc704\ub098 \ud589\uc815\uae30\uad00\uc5d0 \ub300\ud55c \ud589\uc704\ub294 \uadf8\uc5d0 \ud574\ub2f9\ud558\ub294 \uc774 \ubc95\uc5d0 \ub530\ub978 \ud589\uc815\uae30\uad00\uc758 \ud589\uc704\ub098 \ud589\uc815\uae30\uad00\uc5d0 \ub300\ud55c \ud589\uc704\ub85c \ubcf8\ub2e4.\n\n\n\u2463(\ub2e4\ub978 \ubc95\ub839\uacfc\uc758 \uad00\uacc4) \uc774 \ubc95 \uc2dc\ud589 \ub2f9\uc2dc \ub2e4\ub978 \ubc95\ub839\uc5d0\uc11c \uc885\uc804\uc758 \u300c\uc218\ub3c4\uad8c\uc815\ube44\uacc4\ud68d\ubc95\u300d \ub610\ub294 \uadf8 \uaddc\uc815\uc744 \uc778\uc6a9\ud55c \uacbd\uc6b0\uc5d0 \uc774 \ubc95 \uac00\uc6b4\ub370 \uadf8\uc5d0 \ud574\ub2f9\ud558\ub294 \uaddc\uc815\uc774 \uc788\uc73c\uba74 \uc885\uc804\uc758 \uaddc\uc815\uc744 \uac08\uc74c\ud558\uc5ec \uc774 \ubc95 \ub610\ub294 \uc774 \ubc95\uc758 \ud574\ub2f9 \uaddc\uc815\uc744 \uc778\uc6a9\ud55c \uac83\uc73c\ub85c \ubcf8\ub2e4."}, {"@\ubd80\uce59\ud0a4": "2009042209629", "\ubd80\uce59\uacf5\ud3ec\uc77c\uc790": "20090422", "\ubd80\uce59\uacf5\ud3ec\ubc88\ud638": "09629", "\ubd80\uce59\ub0b4\uc6a9": "\ubd80\uce59(\uad6d\uac00\uade0\ud615\ubc1c\uc804 \ud2b9\ubcc4\ubc95) <\uc81c9629\ud638, 2009.4.22>\n\n\n\uc81c1\uc870(\uc2dc\ud589\uc77c) \uc774 \ubc95\uc740 \uacf5\ud3ec\ud55c \ub0a0\ubd80\ud130 \uc2dc\ud589\ud55c\ub2e4. \ub2e4\ub9cc, \u318d\u318d\u318d<\uc0dd\ub7b5>\u318d\u318d\u318d \ubd80\uce59 \uc81c6\uc870\uc81c1\ud56d\u318d\uc81c2\ud56d\u318d\uc81c4\ud56d\u318d\uc81c6\ud56d\u318d\uc81c10\ud56d\u318d\u318d\u318d<\uc0dd\ub7b5>\u318d\u318d\u318d\uc740 2010\ub144 1\uc6d4 1\uc77c\ubd80\ud130 \uac01\uac01 \uc2dc\ud589\ud55c\ub2e4.\n\n\n\uc81c2\uc870\ubd80\ud130 \uc81c5\uc870\uae4c\uc9c0 \uc0dd\ub7b5\n\n\n\uc81c6\uc870(\ub2e4\ub978 \ubc95\ub960\uc758 \uac1c\uc815) \u2460 \ubd80\ud130 \u2468 \uae4c\uc9c0 \uc0dd\ub7b5\n\n\n  \u2469 \uc218\ub3c4\uad8c\uc815\ube44\uacc4\ud68d\ubc95 \uc77c\ubd80\ub97c \ub2e4\uc74c\uacfc \uac19\uc774 \uac1c\uc815\ud55c\ub2e4.\n\n\n  \uc81c16\uc870 \uc911 \"\u300c\uad6d\uac00\uade0\ud615\ubc1c\uc804 \ud2b9\ubcc4\ubc95\u300d\uc5d0 \ub530\ub978 \uad6d\uac00\uade0\ud615\ubc1c\uc804\ud2b9\ubcc4\ud68c\uacc4\"\ub97c \"\u300c\uad6d\uac00\uade0\ud615\ubc1c\uc804 \ud2b9\ubcc4\ubc95\u300d\uc5d0 \ub530\ub978 \uad11\uc5ed\u318d\uc9c0\uc5ed\ubc1c\uc804\ud2b9\ubcc4\ud68c\uacc4\"\ub85c \ud55c\ub2e4.\n\n\n  \u246a \ubd80\ud130 <16> \uae4c\uc9c0 \uc0dd\ub7b5\n\n\n\uc81c7\uc870 \uc0dd\ub7b5"}, {"@\ubd80\uce59\ud0a4": "2010012509968", "\ubd80\uce59\uacf5\ud3ec\uc77c\uc790": "20100125", "\ubd80\uce59\uacf5\ud3ec\ubc88\ud638": "09968", "\ubd80\uce59\ub0b4\uc6a9": "\ubd80\uce59(\ud589\uc815\uc2ec\ud310\ubc95) <\uc81c9968\ud638, 2010.1.25>\n\n\n\uc81c1\uc870(\uc2dc\ud589\uc77c) \uc774 \ubc95\uc740 \uacf5\ud3ec \ud6c4 6\uac1c\uc6d4\uc774 \uacbd\uacfc\ud55c \ub0a0\ubd80\ud130 \uc2dc\ud589\ud55c\ub2e4. <\ub2e8\uc11c \uc0dd\ub7b5>\n\n\n\uc81c2\uc870\ubd80\ud130 \uc81c7\uc870\uae4c\uc9c0 \uc0dd\ub7b5\n\n\n\uc81c8\uc870(\ub2e4\ub978 \ubc95\ub960\uc758 \uac1c\uc815) \u2460 \ubd80\ud130 \u2465 \uae4c\uc9c0 \uc0dd\ub7b5\n\n\n  \u2466 \uc218\ub3c4\uad8c\uc815\ube44\uacc4\ud68d\ubc95 \uc77c\ubd80\ub97c \ub2e4\uc74c\uacfc \uac19\uc774 \uac1c\uc815\ud55c\ub2e4.\n\n\n  \uc81c17\uc870\uc81c2\ud56d \uc911 \"\u300c\ud589\uc815\uc2ec\ud310\ubc95\u300d \uc81c5\uc870\uc640 \uac19\uc740 \ubc95 \uc81c6\uc870\"\ub97c \"\u300c\ud589\uc815\uc2ec\ud310\ubc95\u300d \uc81c6\uc870\"\ub85c \ud55c\ub2e4.\n\n\n  \u2467 \ubd80\ud130 \u2469 \uae4c\uc9c0 \uc0dd\ub7b5\n\n\n\uc81c9\uc870 \uc0dd\ub7b5"}, {"@\ubd80\uce59\ud0a4": "2010033110219", "\ubd80\uce59\uacf5\ud3ec\uc77c\uc790": "20100331", "\ubd80\uce59\uacf5\ud3ec\ubc88\ud638": "10219", "\ubd80\uce59\ub0b4\uc6a9": "\ubd80\uce59(\uc9c0\ubc29\uc138\uae30\ubcf8\ubc95) <\uc81c10219\ud638, 2010.3.31>\n\n\n\uc81c1\uc870(\uc2dc\ud589\uc77c) \uc774 \ubc95\uc740 2011\ub144 1\uc6d4 1\uc77c\ubd80\ud130 \uc2dc\ud589\ud55c\ub2e4. \n\n\n\uc81c2\uc870\ubd80\ud130 \uc81c10\uc870\uae4c\uc9c0 \uc0dd\ub7b5\n\n\n\uc81c11\uc870(\ub2e4\ub978 \ubc95\ub960\uc758 \uac1c\uc815) \u2460 \ubd80\ud130 <24> \uae4c\uc9c0 \uc0dd\ub7b5\n\n\n  <25> \uc218\ub3c4\uad8c\uc815\ube44\uacc4\ud68d\ubc95 \uc77c\ubd80\ub97c \ub2e4\uc74c\uacfc \uac19\uc774 \uac1c\uc815\ud55c\ub2e4.\n\n\n  \uc81c15\uc870\uc81c6\ud56d \uc911 \"\u300c\uc9c0\ubc29\uc138\ubc95\u300d\"\uc744 \"\u300c\uc9c0\ubc29\uc138\uae30\ubcf8\ubc95\u300d\"\uc73c\ub85c \ud55c\ub2e4.\n\n\n  <26> \ubd80\ud130 <61> \uae4c\uc9c0 \uc0dd\ub7b5\n\n\n\uc81c12\uc870 \uc0dd\ub7b5"}, {"@\ubd80\uce59\ud0a4": "2011041410599", "\ubd80\uce59\uacf5\ud3ec\uc77c\uc790": "20110414", "\ubd80\uce59\uacf5\ud3ec\ubc88\ud638": "10599", "\ubd80\uce59\ub0b4\uc6a9": "\ubd80\uce59(\uad6d\ud1a0\uc758 \uacc4\ud68d \ubc0f \uc774\uc6a9\uc5d0 \uad00\ud55c \ubc95\ub960) <\uc81c10599\ud638, 2011.4.14>\n\n\n\uc81c1\uc870(\uc2dc\ud589\uc77c) \uc774 \ubc95\uc740 \uacf5\ud3ec \ud6c4 1\ub144\uc774 \uacbd\uacfc\ud55c \ub0a0\ubd80\ud130 \uc2dc\ud589\ud55c\ub2e4. <\ub2e8\uc11c \uc0dd\ub7b5>\n\n\n\uc81c2\uc870\ubd80\ud130 \uc81c7\uc870\uae4c\uc9c0 \uc0dd\ub7b5\n\n\n\uc81c8\uc870(\ub2e4\ub978 \ubc95\ub960\uc758 \uac1c\uc815) \u2460\ubd80\ud130 <39>\uae4c\uc9c0 \uc0dd\ub7b5\n\n\n  <40> \uc218\ub3c4\uad8c\uc815\ube44\uacc4\ud68d\ubc95 \uc77c\ubd80\ub97c \ub2e4\uc74c\uacfc \uac19\uc774 \uac1c\uc815\ud55c\ub2e4.\n\n\n  \uc81c3\uc870\uc81c1\ud56d \ubcf8\ubb38 \uc911 \"\ub3c4\uc2dc\uacc4\ud68d\"\uc744 \"\ub3c4\uc2dc\u318d\uad70\uacc4\ud68d\"\uc73c\ub85c \ud55c\ub2e4.\n\n\n  <41>\ubd80\ud130 <83>\uae4c\uc9c0 \uc0dd\ub7b5\n\n\n\uc81c9\uc870 \uc0dd\ub7b5"}, {"@\ubd80\uce59\ud0a4": "2011051910670", "\ubd80\uce59\uacf5\ud3ec\uc77c\uc790": "20110519", "\ubd80\uce59\uacf5\ud3ec\ubc88\ud638": "10670", "\ubd80\uce59\ub0b4\uc6a9": "\ubd80\uce59 <\uc81c10670\ud638,2011.5.19>\n\n\n\uc774 \ubc95\uc740 \uacf5\ud3ec \ud6c4 3\uac1c\uc6d4\uc774 \uacbd\uacfc\ud55c \ub0a0\ubd80\ud130 \uc2dc\ud589\ud55c\ub2e4."}, {"@\ubd80\uce59\ud0a4": "2013032311690", "\ubd80\uce59\uacf5\ud3ec\uc77c\uc790": "20130323", "\ubd80\uce59\uacf5\ud3ec\ubc88\ud638": "11690", "\ubd80\uce59\ub0b4\uc6a9": "\ubd80\uce59(\uc815\ubd80\uc870\uc9c1\ubc95) <\uc81c11690\ud638, 2013.3.23>\n\n\n\uc81c1\uc870(\uc2dc\ud589\uc77c) \u2460 \uc774 \ubc95\uc740 \uacf5\ud3ec\ud55c \ub0a0\ubd80\ud130 \uc2dc\ud589\ud55c\ub2e4. \n\n\n  \u2461 \uc0dd\ub7b5\n\n\n\uc81c2\uc870\ubd80\ud130 \uc81c5\uc870\uae4c\uc9c0 \uc0dd\ub7b5\n\n\n\uc81c6\uc870(\ub2e4\ub978 \ubc95\ub960\uc758 \uac1c\uc815) \u2460\ubd80\ud130 <605>\uae4c\uc9c0 \uc0dd\ub7b5\n\n\n  <606> \uc218\ub3c4\uad8c\uc815\ube44\uacc4\ud68d\ubc95 \uc77c\ubd80\ub97c \ub2e4\uc74c\uacfc \uac19\uc774 \uac1c\uc815\ud55c\ub2e4.\n\n\n  \uc81c4\uc870\uc81c1\ud56d \uac01 \ud638 \uc678\uc758 \ubd80\ubd84, \uac19\uc740 \uc870 \uc81c2\ud56d \ubcf8\ubb38, \uac19\uc740 \uc870 \uc81c3\ud56d, \uc81c5\uc870\uc81c1\ud56d\u318d\uc81c2\ud56d\u318d\uc81c4\ud56d, \uc81c7\uc870\uc81c2\ud56d\uc81c2\ud638 \ub2e8\uc11c, \uc81c11\uc870\uc81c1\ud56d\u318d\uc81c2\ud56d, \uc81c14\uc870\uc81c2\ud56d, \uc81c18\uc870\uc81c1\ud56d\u318d\uc81c2\ud56d, \uc81c19\uc870\uc81c1\ud56d \uc804\ub2e8 \ubc0f \ud6c4\ub2e8, \uc81c21\uc870\uc81c1\ud56d, \uc81c22\uc870\uc81c2\ud56d, \uac19\uc740 \uc870 \uc81c3\ud56d\uc81c3\ud638, \uc81c25\uc870, \uc81c26\uc870\uc81c1\ud56d \ubc0f \uc81c27\uc870 \uc911 \"\uad6d\ud1a0\ud574\uc591\ubd80\uc7a5\uad00\"\uc744 \uac01\uac01 \"\uad6d\ud1a0\uad50\ud1b5\ubd80\uc7a5\uad00\"\uc73c\ub85c \ud55c\ub2e4.\n\n\n  <607>\ubd80\ud130 <710>\uae4c\uc9c0 \uc0dd\ub7b5\n\n\n\uc81c7\uc870 \uc0dd\ub7b5"}, {"@\ubd80\uce59\ud0a4": "2013080611998", "\ubd80\uce59\uacf5\ud3ec\uc77c\uc790": "20130806", "\ubd80\uce59\uacf5\ud3ec\ubc88\ud638": "11998", "\ubd80\uce59\ub0b4\uc6a9": "\ubd80\uce59(\uc9c0\ubc29\uc138\uc678\uc218\uc785\uae08\uc758 \uc9d5\uc218 \ub4f1\uc5d0 \uad00\ud55c \ubc95\ub960) <\uc81c11998\ud638, 2013.8.6>\n\n\n\uc81c1\uc870(\uc2dc\ud589\uc77c) \uc774 \ubc95\uc740 \uacf5\ud3ec \ud6c4 1\ub144\uc774 \uacbd\uacfc\ud55c \ub0a0\ubd80\ud130 \uc2dc\ud589\ud55c\ub2e4.\n\n\n\uc81c2\uc870 \uc0dd\ub7b5\n\n\n\uc81c3\uc870(\ub2e4\ub978 \ubc95\ub960\uc758 \uac1c\uc815) \u2460\ubd80\ud130 <34>\uae4c\uc9c0 \uc0dd\ub7b5\n\n\n  <35> \uc218\ub3c4\uad8c\uc815\ube44\uacc4\ud68d\ubc95 \uc77c\ubd80\ub97c \ub2e4\uc74c\uacfc \uac19\uc774 \uac1c\uc815\ud55c\ub2e4.\n\n\n  \uc81c15\uc870\uc81c5\ud56d \uc911 \"\uc9c0\ubc29\uc138 \uccb4\ub0a9\ucc98\ubd84\uc758 \uc608\uc5d0 \ub530\ub77c \uc9d5\uc218\ud560 \uc218 \uc788\ub2e4\"\ub97c \"\u300c\uc9c0\ubc29\uc138\uc678\uc218\uc785\uae08\uc758 \uc9d5\uc218 \ub4f1\uc5d0 \uad00\ud55c \ubc95\ub960\u300d\uc5d0 \ub530\ub77c \uc9d5\uc218\ud560 \uc218 \uc788\ub2e4\"\ub85c \ud55c\ub2e4.\n\n\n  <36>\ubd80\ud130 <71>\uae4c\uc9c0 \uc0dd\ub7b5"}, {"@\ubd80\uce59\ud0a4": "2014010712215", "\ubd80\uce59\uacf5\ud3ec\uc77c\uc790": "20140107", "\ubd80\uce59\uacf5\ud3ec\ubc88\ud638": "12215", "\ubd80\uce59\ub0b4\uc6a9": "\ubd80\uce59(\uad6d\uac00\uade0\ud615\ubc1c\uc804 \ud2b9\ubcc4\ubc95) <\uc81c12215\ud638, 2014.1.7>\n\n\n\uc81c1\uc870(\uc2dc\ud589\uc77c) \uc774 \ubc95\uc740 \uacf5\ud3ec\ud55c \ub0a0\ubd80\ud130 \uc2dc\ud589\ud55c\ub2e4. \ub2e4\ub9cc\u318d\u318d\u318d<\uc0dd\ub7b5>\u318d\u318d\u318d\ubd80\uce59 \uc81c6\uc870\uc81c1\ud56d, \uc81c2\ud56d, \uc81c5\ud56d\ubd80\ud130 \uc81c8\ud56d\uae4c\uc9c0 \ubc0f \uc81c12\ud56d\uc740 2015\ub144 1\uc6d4 1\uc77c\ubd80\ud130 \uc2dc\ud589\ud55c\ub2e4.\n\n\n\uc81c2\uc870\ubd80\ud130 \uc81c5\uc870\uae4c\uc9c0 \uc0dd\ub7b5\n\n\n\uc81c6\uc870(\ub2e4\ub978 \ubc95\ub960\uc758 \uac1c\uc815) \u2460\ubd80\ud130 \u2466\uae4c\uc9c0 \uc0dd\ub7b5\n\n\n  \u2467 \uc218\ub3c4\uad8c\uc815\ube44\uacc4\ud68d\ubc95 \uc77c\ubd80\ub97c \ub2e4\uc74c\uacfc \uac19\uc774 \uac1c\uc815\ud55c\ub2e4.\n\n\n  \uc81c16\uc870 \uc911 \"\uad11\uc5ed\u318d\uc9c0\uc5ed\ubc1c\uc804\ud2b9\ubcc4\ud68c\uacc4\"\ub97c \"\uc9c0\uc5ed\ubc1c\uc804\ud2b9\ubcc4\ud68c\uacc4\"\ub85c \ud55c\ub2e4.\n\n\n  \u2468\ubd80\ud130 \u246c\uae4c\uc9c0 \uc0dd\ub7b5\n\n\n\uc81c7\uc870 \uc0dd\ub7b5"}, {"@\ubd80\uce59\ud0a4": "2017011714543", "\ubd80\uce59\uacf5\ud3ec\uc77c\uc790": "20170117", "\ubd80\uce59\uacf5\ud3ec\ubc88\ud638": "14543", "\ubd80\uce59\ub0b4\uc6a9": "\ubd80\uce59 <\uc81c14543\ud638,2017.1.17>\n\n\n\uc81c1\uc870(\uc2dc\ud589\uc77c) \uc774 \ubc95\uc740 \uacf5\ud3ec \ud6c4 6\uac1c\uc6d4\uc774 \uacbd\uacfc\ud55c \ub0a0\ubd80\ud130 \uc2dc\ud589\ud55c\ub2e4. \ub2e4\ub9cc, \uc81c22\uc870\uc7582\uc81c1\ud56d\uc81c1\ud638\uc758 \uac1c\uc815\uaddc\uc815\uc740 \uacf5\ud3ec\ud55c \ub0a0\ubd80\ud130 \uc2dc\ud589\ud55c\ub2e4.\n\n\n\uc81c2\uc870(\uac00\uc0b0\uae08\uc5d0 \uad00\ud55c \uc801\uc6a9\ub840) \uc81c15\uc870\uc81c4\ud56d\uc758 \uac1c\uc815\uaddc\uc815\uc740 \uc774 \ubc95 \uc2dc\ud589 \ud6c4 \ubd80\uacfc\ud558\ub294 \ubd80\ub2f4\uae08\ubd80\ud130 \uc801\uc6a9\ud55c\ub2e4.\n\n\n\uc81c3\uc870(\uae08\uce58\uc0b0\uc790 \ub4f1\uc5d0 \ub300\ud55c \uacbd\uacfc\uc870\uce58) \uc81c22\uc870\uc7582\uc81c1\ud56d\uc81c1\ud638\uc758 \uac1c\uc815\uaddc\uc815\uc5d0\ub3c4 \ubd88\uad6c\ud558\uace0 \uac19\uc740 \uac1c\uc815\uaddc\uc815 \uc2dc\ud589 \ub2f9\uc2dc \ubc95\ub960 \uc81c10429\ud638 \ubbfc\ubc95 \uc77c\ubd80\uac1c\uc815\ubc95\ub960 \ubd80\uce59 \uc81c2\uc870\uc5d0 \ub530\ub77c \uae08\uce58\uc0b0 \ub610\ub294 \ud55c\uc815\uce58\uc0b0 \uc120\uace0\uc758 \ud6a8\ub825\uc774 \uc720\uc9c0\ub418\ub294 \uc0ac\ub78c\uc5d0 \ub300\ud558\uc5ec\ub294 \uc885\uc804\uc758 \uaddc\uc815\uc744 \uc801\uc6a9\ud55c\ub2e4."}, {"@\ubd80\uce59\ud0a4": "2017020814567", "\ubd80\uce59\uacf5\ud3ec\uc77c\uc790": "20170208", "\ubd80\uce59\uacf5\ud3ec\ubc88\ud638": "14567", "\ubd80\uce59\ub0b4\uc6a9": "\ubd80\uce59(\ub3c4\uc2dc \ubc0f \uc8fc\uac70\ud658\uacbd\uc815\ube44\ubc95) <\uc81c14567\ud638, 2017.2.8>\n\n\n\uc81c1\uc870(\uc2dc\ud589\uc77c) \uc774 \ubc95\uc740 \uacf5\ud3ec \ud6c4 1\ub144\uc774 \uacbd\uacfc\ud55c \ub0a0\ubd80\ud130 \uc2dc\ud589\ud55c\ub2e4.\n\n\n\uc81c2\uc870\ubd80\ud130 \uc81c38\uc870\uae4c\uc9c0 \uc0dd\ub7b5\n\n\n\uc81c39\uc870(\ub2e4\ub978 \ubc95\ub960\uc758 \uac1c\uc815) \u2460\ubd80\ud130 \u246b\uae4c\uc9c0 \uc0dd\ub7b5\n\n\n  \u246c \uc218\ub3c4\uad8c\uc815\ube44\uacc4\ud68d\ubc95 \uc77c\ubd80\ub97c \ub2e4\uc74c\uacfc \uac19\uc774 \uac1c\uc815\ud55c\ub2e4.\n\n\n  \uc81c13\uc870\uc81c2\ud638 \uc911 \"\ub3c4\uc2dc\ud658\uacbd\uc815\ube44\uc0ac\uc5c5\"\uc744 \"\uc7ac\uac1c\ubc1c\uc0ac\uc5c5\"\uc73c\ub85c \ud55c\ub2e4.\n\n\n  \u246d\ubd80\ud130 <24>\uae4c\uc9c0 \uc0dd\ub7b5\n\n\n\uc81c40\uc870 \uc0dd\ub7b5"}, {"@\ubd80\uce59\ud0a4": "2018032015489", "\ubd80\uce59\uacf5\ud3ec\uc77c\uc790": "20180320", "\ubd80\uce59\uacf5\ud3ec\ubc88\ud638": "15489", "\ubd80\uce59\ub0b4\uc6a9": "\ubd80\uce59(\uad6d\uac00\uade0\ud615\ubc1c\uc804 \ud2b9\ubcc4\ubc95) <\uc81c15489\ud638, 2018.3.20>\n\n\n\uc81c1\uc870(\uc2dc\ud589\uc77c) \uc774 \ubc95\uc740 \uacf5\ud3ec\ud55c \ub0a0\ubd80\ud130 \uc2dc\ud589\ud55c\ub2e4. <\ub2e8\uc11c \uc0dd\ub7b5>\n\n\n\uc81c2\uc870\ubd80\ud130 \uc81c5\uc870\uae4c\uc9c0 \uc0dd\ub7b5\n\n\n\uc81c6\uc870(\ub2e4\ub978 \ubc95\ub960\uc758 \uac1c\uc815) \u2460\ubd80\ud130 \u246c\uae4c\uc9c0 \uc0dd\ub7b5\n\n\n  \u246d \uc218\ub3c4\uad8c\uc815\ube44\uacc4\ud68d\ubc95 \uc77c\ubd80\ub97c \ub2e4\uc74c\uacfc \uac19\uc774 \uac1c\uc815\ud55c\ub2e4.\n\n\n  \uc81c16\uc870 \uc911 \"\u300c\uad6d\uac00\uade0\ud615\ubc1c\uc804 \ud2b9\ubcc4\ubc95\u300d\uc5d0 \ub530\ub978 \uc9c0\uc5ed\ubc1c\uc804\ud2b9\ubcc4\ud68c\uacc4\"\ub97c \"\u300c\uad6d\uac00\uade0\ud615\ubc1c\uc804 \ud2b9\ubcc4\ubc95\u300d\uc5d0 \ub530\ub978 \uad6d\uac00\uade0\ud615\ubc1c\uc804\ud2b9\ubcc4\ud68c\uacc4\"\ub85c \ud55c\ub2e4. \n\n\n  \u246e\ubd80\ud130 <20>\uae4c\uc9c0 \uc0dd\ub7b5\n\n\n\uc81c7\uc870 \uc0dd\ub7b5"}, {"@\ubd80\uce59\ud0a4": "2018061215680", "\ubd80\uce59\uacf5\ud3ec\uc77c\uc790": "20180612", "\ubd80\uce59\uacf5\ud3ec\ubc88\ud638": "15680", "\ubd80\uce59\ub0b4\uc6a9": "\ubd80\uce59 <\uc81c15680\ud638,2018.6.12>\n\n\n\uc81c1\uc870(\uc2dc\ud589\uc77c) \uc774 \ubc95\uc740 \uacf5\ud3ec\ud55c \ub0a0\ubd80\ud130 \uc2dc\ud589\ud55c\ub2e4.\n\n\n\uc81c2\uc870(\ucd1d\ub7c9\uaddc\uc81c\uc5d0 \uad00\ud55c \uc801\uc6a9\ub840) \uc81c18\uc870\uc81c1\ud56d \ud6c4\ub2e8\uc758 \uac1c\uc815\uaddc\uc815\uc740 \uc774 \ubc95 \uc2dc\ud589 \ud6c4 \ucd5c\ucd08\ub85c \ucd1d\ud5c8\uc6a9\ub7c9\uc744 \uc815\ud558\uac70\ub098 \ubcc0\uacbd\ud558\ub294 \uacbd\uc6b0\ubd80\ud130 \uc801\uc6a9\ud55c\ub2e4."}]}, "\uac1c\uc815\ubb38": {"\uac1c\uc815\ubb38\ub0b4\uc6a9": "\uad6d\ud68c\uc5d0\uc11c \uc758\uacb0\ub41c \uc218\ub3c4\uad8c\uc815\ube44\uacc4\ud68d\ubc95 \uc77c\ubd80\uac1c\uc815\ubc95\ub960\uc744 \uc774\uc5d0 \uacf5\ud3ec\ud55c\ub2e4.\n\n\n          \ub300\ud1b5\ub839        \ubb38\uc7ac\uc778 (\uc778)\n\n\n    2018\ub144 6\uc6d4 12\uc77c\n\n\n          \uad6d\ubb34\ucd1d\ub9ac        \uc774\ub099\uc5f0\n\n\n          \uad6d\ubb34\uc704\uc6d0 \uad6d\ud1a0\uad50\ud1b5\ubd80 \uc7a5\uad00        \uae40\ud604\ubbf8\n\n\n\n\n\n\n\u2299\ubc95\ub960 \uc81c15680\ud638\n\n\n\uc218\ub3c4\uad8c\uc815\ube44\uacc4\ud68d\ubc95 \uc77c\ubd80\uac1c\uc815\ubc95\ub960\n\n\n\n\n\n\n\uc218\ub3c4\uad8c\uc815\ube44\uacc4\ud68d\ubc95 \uc77c\ubd80\ub97c \ub2e4\uc74c\uacfc \uac19\uc774 \uac1c\uc815\ud55c\ub2e4.\n\n\n\n\n\n\n\uc81c18\uc870\uc81c1\ud56d\uc5d0 \ud6c4\ub2e8\uc744 \ub2e4\uc74c\uacfc \uac19\uc774 \uc2e0\uc124\ud55c\ub2e4.\n\n\n  \uc774 \uacbd\uc6b0 \uad6d\ud1a0\uad50\ud1b5\ubd80\uc7a5\uad00\uc740 \ucd1d\ud5c8\uc6a9\ub7c9\uacfc \uadf8 \uc0b0\ucd9c \uadfc\uac70\ub97c \uace0\uc2dc\ud558\uc5ec\uc57c \ud55c\ub2e4.\n\n\n\n\n\n\n          \ubd80\uce59\n\n\n\uc81c1\uc870(\uc2dc\ud589\uc77c) \uc774 \ubc95\uc740 \uacf5\ud3ec\ud55c \ub0a0\ubd80\ud130 \uc2dc\ud589\ud55c\ub2e4.\n\n\n\uc81c2\uc870(\ucd1d\ub7c9\uaddc\uc81c\uc5d0 \uad00\ud55c \uc801\uc6a9\ub840) \uc81c18\uc870\uc81c1\ud56d \ud6c4\ub2e8\uc758 \uac1c\uc815\uaddc\uc815\uc740 \uc774 \ubc95 \uc2dc\ud589 \ud6c4 \ucd5c\ucd08\ub85c \ucd1d\ud5c8\uc6a9\ub7c9\uc744 \uc815\ud558\uac70\ub098 \ubcc0\uacbd\ud558\ub294 \uacbd\uc6b0\ubd80\ud130 \uc801\uc6a9\ud55c\ub2e4."}, "\uc81c\uac1c\uc815\uc774\uc720": {"\uc81c\uac1c\uc815\uc774\uc720\ub0b4\uc6a9": "[\uc77c\ubd80\uac1c\uc815]\n\n\n\u25c7 \uac1c\uc815\uc774\uc720 \ubc0f \uc8fc\uc694\ub0b4\uc6a9\n\n\n  \ud604\ud589\ubc95\uc740 \uc218\ub3c4\uad8c\uc758 \uc9c8\uc11c \uc788\ub294 \uc815\ube44 \ubc0f \uade0\ud615 \ubc1c\uc804\uc744 \uc704\ud558\uc5ec \uc218\ub3c4\uad8c \ub0b4 \uc778\uad6c\uc9d1\uc911\uc720\ubc1c\uc2dc\uc124 \uc2e0\uc124 \ubc0f \uc99d\uc124\uc5d0 \ub300\ud55c \ucd1d\ub7c9\uaddc\uc81c \uc81c\ub3c4\ub97c \ub450\uace0 \uc788\uc73c\ub098, \ub9e4\ub144 \uacfc\ub3c4\ud55c \ucd1d\ud5c8\uc6a9\ub7c9\uc744 \uc815\ud558\uc5ec \uc2e4\uc9c8\uc801\uc73c\ub85c \ucd1d\ub7c9\uaddc\uc81c\uac00 \uc720\uba85\ubb34\uc2e4\ud654\ub41c \uc2e4\uc815\uc784.\n\n\n  \ud2b9\ud788 \uc11c\uc6b8\uc2dc, \uc778\ucc9c, \uacbd\uae30\ub3c4 \ub4f1 \uc218\ub3c4\uad8c \ub0b4 \uc778\uad6c\uc9d1\uc911\uc720\ubc1c\uc2dc\uc124 \uc2e0\uc124 \ubc0f \uc99d\uc124 \uac1c\ubc1c\uc2e4\uc801\uc744 \uc0b4\ud3b4\ubcf4\uba74, \ub9e4\ub144 \uac1c\ubc1c\uc2e4\uc801\ubcf4\ub2e4 \ucd1d\ud5c8\uc6a9\ub7c9\uc774 \uacfc\ub3c4\ud558\uac8c \ud074 \ubfd0\ub9cc \uc544\ub2c8\ub77c, \ucd1d\ud5c8\uc6a9\ub7c9\uc744 \uacb0\uc815\ud558\ub294 \uc218\ub3c4\uad8c\uc815\ube44\uc704\uc6d0\ud68c \uc2ec\uc758\ub3c4 \ube44\uacf5\uac1c\ub428\uc5d0 \ub530\ub77c \ucd1d\ud5c8\uc6a9\ub7c9 \uacb0\uc815\uc758 \uc815\ub2f9\uc131\uc744 \ud655\ubcf4\ud558\uc9c0 \ubabb\ud558\uace0 \uc788\uc74c.\n\n\n  \uc774\uc5d0 \uac1c\uc815\uc548\uc740 \uad6d\ud1a0\uad50\ud1b5\ubd80\uc7a5\uad00\uc774 \uc778\uad6c\uc9d1\uc911\uc720\ubc1c\uc2dc\uc124 \uc2e0\uc124 \ubc0f \uc99d\uc124\uc758 \ucd1d\ud5c8\uc6a9\ub7c9\uc744 \uc815\ud558\ub294 \uacbd\uc6b0 \ucd1d\ud5c8\uc6a9\ub7c9\uacfc \uc774\uc5d0 \ub300\ud55c \uc0b0\ucd9c \uadfc\uac70\ub97c \uace0\uc2dc\ud558\ub3c4\ub85d \ud568\uc73c\ub85c\uc368 \ucd1d\ub7c9\uaddc\uc81c \uc81c\ub3c4\uac00 \ud22c\uba85\ud558\uace0 \ud569\ub9ac\uc801\uc73c\ub85c \uc6b4\uc601\ub420 \uc218 \uc788\ub3c4\ub85d \ud558\ub824\ub294 \uac83\uc784.\n\n\n<\ubc95\uc81c\ucc98 \uc81c\uacf5>"}}}}