{"root": {"\ubc95\ub839": {"@\ubc95\ub839\ud0a4": "0011732009013009365", "\uae30\ubcf8\uc815\ubcf4": {"\ubc95\ub839ID": "001173", "\uacf5\ud3ec\uc77c\uc790": "20090130", "\uacf5\ud3ec\ubc88\ud638": "09365", "\uc5b8\uc5b4": "\ud55c\uae00", "\ubc95\uc885\uad6c\ubd84": {"@\ubc95\uc885\uad6c\ubd84\ucf54\ub4dc": "A0002", "#text": "\ubc95\ub960"}, "\ubc95\ub839\uba85_\ud55c\uae00": "\ud63c\uc778\uc2e0\uace0\ud2b9\ub840\ubc95", "\ubc95\ub839\uba85_\ud55c\uc790": "\ud63c\uc778\uc2e0\uace0\ud2b9\ub840\ubc95", "\ubc95\ub839\uba85\uc57d\uce6d": null, "\uc81c\uba85\ubcc0\uacbd\uc5ec\ubd80": "N", "\ud55c\uae00\ubc95\ub839\uc5ec\ubd80": "N", "\ud3b8\uc7a5\uc808\uad00": "08060000", "\uc18c\uad00\ubd80\ucc98": {"@\uc18c\uad00\ubd80\ucc98\ucf54\ub4dc": "1270000", "#text": "\ubc95\ubb34\ubd80"}, "\uc2dc\ud589\uc77c\uc790": "20090130", "\uc81c\uac1c\uc815\uad6c\ubd84": "\uc77c\ubd80\uac1c\uc815", "\uc81c\uc548\uad6c\ubd84": "\uc815\ubd80", "\uc758\uacb0\uad6c\ubd84": "\uad6d\ud68c", "\uc774\uc804\ubc95\ub839\uba85": "\ud63c\uc778\uc2e0\uace0\ud2b9\ub840\ubc95", "\ubcc4\ud45c\ud3b8\uc9d1\uc5ec\ubd80": "Y", "\uacf5\ud3ec\ubc95\ub839\uc5ec\ubd80": "Y"}, "\uc870\ubb38": {"\uc870\ubb38\ub2e8\uc704": [{"@\uc870\ubb38\ud0a4": "0001001", "\uc870\ubb38\ubc88\ud638": "1", "\uc870\ubb38\uc5ec\ubd80": "\uc870\ubb38", "\uc870\ubb38\uc81c\ubaa9": "\ubaa9\uc801", "\uc870\ubb38\uc2dc\ud589\uc77c\uc790": "20090130", "\uc870\ubb38\uc81c\uac1c\uc815\uc720\ud615": "\uc804\ubb38\uac1c\uc815", "\uc870\ubb38\uc81c\uac1c\uc815\uc77c\uc790\ubb38\uc790\uc5f4": "2009.1.30", "\uc870\ubb38\uc774\ub3d9\uc774\uc804": "000000", "\uc870\ubb38\uc774\ub3d9\uc774\ud6c4": "000000", "\uc870\ubb38\ubcc0\uacbd\uc5ec\ubd80": "1", "\uc870\ubb38\ub0b4\uc6a9": "\uc81c1\uc870 (\ubaa9\uc801) \uc774 \ubc95\uc740 \ud63c\uc778 \ub2f9\uc0ac\uc790 \uc911 \uc5b4\ub290 \ud55c\ucabd\uc774 \uc804\uc7c1\uc774\ub098 \uc0ac\ubcc0(\u4e8b\u8b8a)\uc73c\ub85c \uc804\ud22c\uc5d0 \ucc38\uac00\ud558\uac70\ub098 \uc804\ud22c \uc218\ud589\uc744 \uc704\ud55c \uacf5\ubb34(\u516c\u52d9)\uc5d0 \uc885\uc0ac\ud568\uc73c\ub85c \uc778\ud558\uc5ec \ud63c\uc778\uc2e0\uace0\ub97c \ud558\uc9c0 \ubabb\ud558\uace0 \uc0ac\ub9dd\ud55c \uacbd\uc6b0\uc5d0 \uad00\ud55c \ud2b9\uce59(\u7279\u5247)\uc744 \uaddc\uc815\ud568\uc744 \ubaa9\uc801\uc73c\ub85c \ud55c\ub2e4.", "\uc870\ubb38\ucc38\uace0\uc790\ub8cc": "[\uc804\ubb38\uac1c\uc815 2009.1.30]"}, {"@\uc870\ubb38\ud0a4": "0002001", "\uc870\ubb38\ubc88\ud638": "2", "\uc870\ubb38\uc5ec\ubd80": "\uc870\ubb38", "\uc870\ubb38\uc81c\ubaa9": "\ud63c\uc778\uc2e0\uace0", "\uc870\ubb38\uc2dc\ud589\uc77c\uc790": "20090130", "\uc870\ubb38\uc81c\uac1c\uc815\uc720\ud615": "\uc804\ubb38\uac1c\uc815", "\uc870\ubb38\uc81c\uac1c\uc815\uc77c\uc790\ubb38\uc790\uc5f4": "2009.1.30", "\uc870\ubb38\uc774\ub3d9\uc774\uc804": "000000", "\uc870\ubb38\uc774\ub3d9\uc774\ud6c4": "000000", "\uc870\ubb38\ubcc0\uacbd\uc5ec\ubd80": "1", "\uc870\ubb38\ub0b4\uc6a9": "\uc81c2\uc870 (\ud63c\uc778\uc2e0\uace0) \ud63c\uc778\uc2e0\uace0 \uc758\ubb34\uc790 \uc911 \uc5b4\ub290 \ud55c\ucabd\uc774 \uc81c1\uc870\uc5d0 \ub530\ub978 \uc0ac\uc720\ub85c \uc0ac\ub9dd\ud55c \uacbd\uc6b0\uc5d0\ub294 \uc0dd\uc874\ud55c \ub2f9\uc0ac\uc790\uac00 \uac00\uc815\ubc95\uc6d0\uc758 \ud655\uc778\uc744 \ubc1b\uc544 \ub2e8\ub3c5\uc73c\ub85c \ud63c\uc778\uc2e0\uace0\ub97c \ud560 \uc218 \uc788\ub2e4.", "\uc870\ubb38\ucc38\uace0\uc790\ub8cc": "[\uc804\ubb38\uac1c\uc815 2009.1.30]"}, {"@\uc870\ubb38\ud0a4": "0003001", "\uc870\ubb38\ubc88\ud638": "3", "\uc870\ubb38\uc5ec\ubd80": "\uc870\ubb38", "\uc870\ubb38\uc81c\ubaa9": "\ud655\uc778\uc7ac\ud310 \uad00\ud560", "\uc870\ubb38\uc2dc\ud589\uc77c\uc790": "20090130", "\uc870\ubb38\uc81c\uac1c\uc815\uc720\ud615": "\uc804\ubb38\uac1c\uc815", "\uc870\ubb38\uc81c\uac1c\uc815\uc77c\uc790\ubb38\uc790\uc5f4": "2009.1.30", "\uc870\ubb38\uc774\ub3d9\uc774\uc804": "000000", "\uc870\ubb38\uc774\ub3d9\uc774\ud6c4": "000000", "\uc870\ubb38\ubcc0\uacbd\uc5ec\ubd80": "1", "\uc870\ubb38\ub0b4\uc6a9": "\uc81c3\uc870 (\ud655\uc778\uc7ac\ud310 \uad00\ud560) \uc81c2\uc870\uc758 \ud655\uc778\uc740 \uc0ac\ub9dd\ud55c \ub2f9\uc0ac\uc790\uc758 \ub9c8\uc9c0\ub9c9 \uc8fc\uc18c\uc9c0\uac00 \uc788\ub294 \uacf3\uc758 \uac00\uc815\ubc95\uc6d0\uc774 \uad00\ud560\ud55c\ub2e4.", "\uc870\ubb38\ucc38\uace0\uc790\ub8cc": "[\uc804\ubb38\uac1c\uc815 2009.1.30]"}, {"@\uc870\ubb38\ud0a4": "0004001", "\uc870\ubb38\ubc88\ud638": "4", "\uc870\ubb38\uc5ec\ubd80": "\uc870\ubb38", "\uc870\ubb38\uc81c\ubaa9": "\uc2e0\uace0\uc758 \ud6a8\ub825", "\uc870\ubb38\uc2dc\ud589\uc77c\uc790": "20090130", "\uc870\ubb38\uc81c\uac1c\uc815\uc720\ud615": "\uc804\ubb38\uac1c\uc815", "\uc870\ubb38\uc81c\uac1c\uc815\uc77c\uc790\ubb38\uc790\uc5f4": "2009.1.30", "\uc870\ubb38\uc774\ub3d9\uc774\uc804": "000000", "\uc870\ubb38\uc774\ub3d9\uc774\ud6c4": "000000", "\uc870\ubb38\ubcc0\uacbd\uc5ec\ubd80": "1", "\uc870\ubb38\ub0b4\uc6a9": "\uc81c4\uc870 (\uc2e0\uace0\uc758 \ud6a8\ub825) \uc81c2\uc870\uc5d0 \ub530\ub978 \uc2e0\uace0\uac00 \uc788\ub294 \uacbd\uc6b0\uc5d0\ub294 \uc2e0\uace0 \uc758\ubb34\uc790 \uc5b4\ub290 \ud55c\ucabd\uc758 \uc0ac\ub9dd \uc2dc\uc5d0 \uc2e0\uace0\uac00 \uc788\uc5c8\ub358 \uac83\uc73c\ub85c \ubcf8\ub2e4.", "\uc870\ubb38\ucc38\uace0\uc790\ub8cc": "[\uc804\ubb38\uac1c\uc815 2009.1.30]"}, {"@\uc870\ubb38\ud0a4": "0005001", "\uc870\ubb38\ubc88\ud638": "5", "\uc870\ubb38\uc5ec\ubd80": "\uc870\ubb38", "\uc870\ubb38\uc81c\ubaa9": "\uc801\uc6a9 \ubc94\uc704", "\uc870\ubb38\uc2dc\ud589\uc77c\uc790": "20090130", "\uc870\ubb38\uc81c\uac1c\uc815\uc720\ud615": "\uc804\ubb38\uac1c\uc815", "\uc870\ubb38\uc81c\uac1c\uc815\uc77c\uc790\ubb38\uc790\uc5f4": "2009.1.30", "\uc870\ubb38\uc774\ub3d9\uc774\uc804": "000000", "\uc870\ubb38\uc774\ub3d9\uc774\ud6c4": "000000", "\uc870\ubb38\ubcc0\uacbd\uc5ec\ubd80": "1", "\uc870\ubb38\ub0b4\uc6a9": "\uc81c5\uc870 (\uc801\uc6a9 \ubc94\uc704) \uc81c1\uc870\uc5d0 \ub530\ub978 \uc804\ud22c \ub610\ub294 \uc804\ud22c \uc218\ud589\uc744 \uc704\ud55c \uacf5\ubb34\uc5d0 \uad00\ud55c \uc0ac\ud56d\uc740 \ub300\ud1b5\ub839\ub839\uc73c\ub85c \uc815\ud55c\ub2e4.", "\uc870\ubb38\ucc38\uace0\uc790\ub8cc": "[\uc804\ubb38\uac1c\uc815 2009.1.30]"}]}, "\ubd80\uce59": {"\ubd80\uce59\ub2e8\uc704": [{"@\ubd80\uce59\ud0a4": "1968123102067", "\ubd80\uce59\uacf5\ud3ec\uc77c\uc790": "19681231", "\ubd80\uce59\uacf5\ud3ec\ubc88\ud638": "02067", "\ubd80\uce59\ub0b4\uc6a9": "\ubd80\uce59  <\uc81c2067\ud638,1968.12.31>\n\n\n\uc774 \ubc95\uc740 \uacf5\ud3ec\ud55c \ub0a0\ub85c\ubd80\ud130 \uc2dc\ud589\ud55c\ub2e4."}, {"@\ubd80\uce59\ud0a4": "2009013009365", "\ubd80\uce59\uacf5\ud3ec\uc77c\uc790": "20090130", "\ubd80\uce59\uacf5\ud3ec\ubc88\ud638": "09365", "\ubd80\uce59\ub0b4\uc6a9": "\ubd80\uce59 <\uc81c9365\ud638,2009.1.30>\n\n\n\uc774 \ubc95\uc740 \uacf5\ud3ec\ud55c \ub0a0\ubd80\ud130 \uc2dc\ud589\ud55c\ub2e4."}]}, "\uac1c\uc815\ubb38": {"\uac1c\uc815\ubb38\ub0b4\uc6a9": "\uad6d\ud68c\uc5d0\uc11c \uc758\uacb0\ub41c \ud63c\uc778\uc2e0\uace0\ud2b9\ub840\ubc95 \uc77c\ubd80\uac1c\uc815\ubc95\ub960\uc744 \uc774\uc5d0 \uacf5\ud3ec\ud55c\ub2e4.\n\n\n          \ub300\ud1b5\ub839        \uc774 \uba85 \ubc15 (\uc778)\n\n\n    2009\ub144 1\uc6d4 30\uc77c\n\n\n          \uad6d\ubb34\ucd1d\ub9ac        \ud55c \uc2b9 \uc218\n\n\n          \uad6d\ubb34\uc704\uc6d0 \ubc95\ubb34\ubd80 \uc7a5\uad00        \uae40 \uacbd \ud55c\n\n\n\u2299\ubc95\ub960 \uc81c9365\ud638\n\n\n\ud63c\uc778\uc2e0\uace0\ud2b9\ub840\ubc95 \uc77c\ubd80\uac1c\uc815\ubc95\ub960\n\n\n\ud63c\uc778\uc2e0\uace0\ud2b9\ub840\ubc95 \uc77c\ubd80\ub97c \ub2e4\uc74c\uacfc \uac19\uc774 \uac1c\uc815\ud55c\ub2e4.\n\n\n\uc81c\uba85 \u201c\ud63c\uc778\uc2e0\uace0\ud2b9\ub840\ubc95\u201d\uc744 \u201c\ud63c\uc778\uc2e0\uace0\ud2b9\ub840\ubc95\u201d\uc73c\ub85c \ud55c\ub2e4.\n\n\n\uc81c1\uc870\ubd80\ud130 \uc81c5\uc870\uae4c\uc9c0\ub97c \uac01\uac01 \ub2e4\uc74c\uacfc \uac19\uc774 \ud55c\ub2e4.\n\n\n\uc81c1\uc870(\ubaa9\uc801) \uc774 \ubc95\uc740 \ud63c\uc778 \ub2f9\uc0ac\uc790 \uc911 \uc5b4\ub290 \ud55c\ucabd\uc774 \uc804\uc7c1\uc774\ub098 \uc0ac\ubcc0(\u4e8b\u8b8a)\uc73c\ub85c \uc804\ud22c\uc5d0 \ucc38\uac00\ud558\uac70\ub098 \uc804\ud22c \uc218\ud589\uc744 \uc704\ud55c \uacf5\ubb34(\u516c\u52d9)\uc5d0 \uc885\uc0ac\ud568\uc73c\ub85c \uc778\ud558\uc5ec \ud63c\uc778\uc2e0\uace0\ub97c \ud558\uc9c0 \ubabb\ud558\uace0 \uc0ac\ub9dd\ud55c \uacbd\uc6b0\uc5d0 \uad00\ud55c \ud2b9\uce59(\u7279\u5247)\uc744 \uaddc\uc815\ud568\uc744 \ubaa9\uc801\uc73c\ub85c \ud55c\ub2e4.\n\n\n\uc81c2\uc870(\ud63c\uc778\uc2e0\uace0) \ud63c\uc778\uc2e0\uace0 \uc758\ubb34\uc790 \uc911 \uc5b4\ub290 \ud55c\ucabd\uc774 \uc81c1\uc870\uc5d0 \ub530\ub978 \uc0ac\uc720\ub85c \uc0ac\ub9dd\ud55c \uacbd\uc6b0\uc5d0\ub294 \uc0dd\uc874\ud55c \ub2f9\uc0ac\uc790\uac00 \uac00\uc815\ubc95\uc6d0\uc758 \ud655\uc778\uc744 \ubc1b\uc544 \ub2e8\ub3c5\uc73c\ub85c \ud63c\uc778\uc2e0\uace0\ub97c \ud560 \uc218 \uc788\ub2e4.\n\n\n\uc81c3\uc870(\ud655\uc778\uc7ac\ud310 \uad00\ud560) \uc81c2\uc870\uc758 \ud655\uc778\uc740 \uc0ac\ub9dd\ud55c \ub2f9\uc0ac\uc790\uc758 \ub9c8\uc9c0\ub9c9 \uc8fc\uc18c\uc9c0\uac00 \uc788\ub294 \uacf3\uc758 \uac00\uc815\ubc95\uc6d0\uc774 \uad00\ud560\ud55c\ub2e4.\n\n\n\uc81c4\uc870(\uc2e0\uace0\uc758 \ud6a8\ub825) \uc81c2\uc870\uc5d0 \ub530\ub978 \uc2e0\uace0\uac00 \uc788\ub294 \uacbd\uc6b0\uc5d0\ub294 \uc2e0\uace0 \uc758\ubb34\uc790 \uc5b4\ub290 \ud55c\ucabd\uc758 \uc0ac\ub9dd \uc2dc\uc5d0 \uc2e0\uace0\uac00 \uc788\uc5c8\ub358 \uac83\uc73c\ub85c \ubcf8\ub2e4.\n\n\n\uc81c5\uc870(\uc801\uc6a9 \ubc94\uc704) \uc81c1\uc870\uc5d0 \ub530\ub978 \uc804\ud22c \ub610\ub294 \uc804\ud22c \uc218\ud589\uc744 \uc704\ud55c \uacf5\ubb34\uc5d0 \uad00\ud55c \uc0ac\ud56d\uc740 \ub300\ud1b5\ub839\ub839\uc73c\ub85c \uc815\ud55c\ub2e4.\n\n\n          \ubd80\uce59\n\n\n\uc774 \ubc95\uc740 \uacf5\ud3ec\ud55c \ub0a0\ubd80\ud130 \uc2dc\ud589\ud55c\ub2e4."}, "\uc81c\uac1c\uc815\uc774\uc720": {"\uc81c\uac1c\uc815\uc774\uc720\ub0b4\uc6a9": "[\uc77c\ubd80\uac1c\uc815]\n\n\n\u25c7\uac1c\uc815\uc774\uc720 \ubc0f \uc8fc\uc694\ub0b4\uc6a9\n\n\n  \ubc95 \ubb38\uc7a5\uc744 \uc6d0\uce59\uc801\uc73c\ub85c \ud55c\uae00\ub85c \uc801\uace0, \uc5b4\ub824\uc6b4 \uc6a9\uc5b4\ub97c \uc26c\uc6b4 \uc6a9\uc5b4\ub85c \ubc14\uafb8\uba70, \uae38\uace0 \ubcf5\uc7a1\ud55c \ubb38\uc7a5\uc740 \uccb4\uacc4 \ub4f1\uc744 \uc815\ube44\ud558\uc5ec \uac04\uacb0\ud558\uac8c \ud558\ub294 \ub4f1 \uad6d\ubbfc\uc774 \ubc95 \ubb38\uc7a5\uc744 \uc774\ud574\ud558\uae30 \uc27d\uac8c \uc815\ube44\ud558\ub824\ub294 \uac83\uc784."}}}}